[{"code":"BCT16-7604S","name":"Tribute Yellow","notes":"","variant":"","file":"","id":"1800","red":"244","green":"195","blue":"93","interior":0,"product":[{"id":"99","name":"<span class='boysen-name'>BOYSEN<span class='boysen-reg'>&reg;</span><span class='boysen-reg-holder'>&reg;</span></span> Color Trend 2016","subtitle":"","image":"data\/0.jpg"}]},{"code":"BCT16-7709S","name":"Star Princess","notes":"","variant":"","file":"","id":"1801","red":"214","green":"160","blue":"176","interior":0,"product":[{"id":"99","name":"<span class='boysen-name'>BOYSEN<span class='boysen-reg'>&reg;</span><span class='boysen-reg-holder'>&reg;</span></span> Color Trend 2016","subtitle":"","image":"data\/0.jpg"}]},{"code":"BCT16-7710S","name":"Dune Buggy","notes":"","variant":"","file":"","id":"1802","red":"210","green":"123","blue":"54","interior":0,"product":[{"id":"99","name":"<span class='boysen-name'>BOYSEN<span class='boysen-reg'>&reg;</span><span class='boysen-reg-holder'>&reg;</span></span> Color Trend 2016","subtitle":"","image":"data\/0.jpg"}]},{"code":"BCT17-7412S","name":"Designer Denim","notes":"","variant":"","file":"","id":"1806","red":"0","green":"51","blue":"90","interior":0,"product":[{"id":"100","name":"<span class='boysen-name'>BOYSEN<span class='boysen-reg'>&reg;</span><span class='boysen-reg-holder'>&reg;</span></span> Color Trend 2017","subtitle":"","image":"data\/0.jpg"}]},{"code":"BCT17-7413S","name":"Rebel Yell","notes":"","variant":"","file":"","id":"1807","red":"35","green":"86","blue":"152","interior":0,"product":[{"id":"100","name":"<span class='boysen-name'>BOYSEN<span class='boysen-reg'>&reg;</span><span class='boysen-reg-holder'>&reg;</span></span> Color Trend 2017","subtitle":"","image":"data\/0.jpg"}]},{"code":"BCT17-7509S","name":"High Society","notes":"","variant":"","file":"","id":"1808","red":"161","green":"175","blue":"160","interior":0,"product":[{"id":"100","name":"<span class='boysen-name'>BOYSEN<span class='boysen-reg'>&reg;</span><span class='boysen-reg-holder'>&reg;</span></span> Color Trend 2017","subtitle":"","image":"data\/0.jpg"}]},{"code":"BCT17-7719S","name":"Tuscan Sun","notes":"","variant":"","file":"","id":"1809","red":"212","green":"163","blue":"0","interior":1,"product":[{"id":"100","name":"<span class='boysen-name'>BOYSEN<span class='boysen-reg'>&reg;</span><span class='boysen-reg-holder'>&reg;</span></span> Color Trend 2017","subtitle":"","image":"data\/0.jpg"}]},{"code":"BCT17-7720S","name":"Fine Wine","notes":"","variant":"","file":"","id":"1810","red":"117","green":"41","blue":"53","interior":0,"product":[{"id":"100","name":"<span class='boysen-name'>BOYSEN<span class='boysen-reg'>&reg;</span><span class='boysen-reg-holder'>&reg;</span></span> Color Trend 2017","subtitle":"","image":"data\/0.jpg"}]},{"code":"BCT17-7721S","name":"Pink of Wealth","notes":"","variant":"","file":"","id":"1811","red":"190","green":"102","blue":"127","interior":0,"product":[{"id":"100","name":"<span class='boysen-name'>BOYSEN<span class='boysen-reg'>&reg;</span><span class='boysen-reg-holder'>&reg;</span></span> Color Trend 2017","subtitle":"","image":"data\/0.jpg"}]},{"code":"BCT17-7411S","name":"Underground Harbor","notes":"","variant":"","file":"","id":"1812","red":"53","green":"106","blue":"122","interior":0,"product":[{"id":"100","name":"<span class='boysen-name'>BOYSEN<span class='boysen-reg'>&reg;</span><span class='boysen-reg-holder'>&reg;</span></span> Color Trend 2017","subtitle":"","image":"data\/0.jpg"}]},{"code":"BCT17-7718S","name":"Barenaked","notes":"","variant":"","file":"","id":"1813","red":"207","green":"194","blue":"186","interior":0,"product":[{"id":"100","name":"<span class='boysen-name'>BOYSEN<span class='boysen-reg'>&reg;</span><span class='boysen-reg-holder'>&reg;</span></span> Color Trend 2017","subtitle":"","image":"data\/0.jpg"}]},{"code":"BCT17-7804S","name":"Basic Blend","notes":"","variant":"","file":"","id":"1814","red":"174","green":"162","blue":"138","interior":0,"product":[{"id":"100","name":"<span class='boysen-name'>BOYSEN<span class='boysen-reg'>&reg;</span><span class='boysen-reg-holder'>&reg;</span></span> Color Trend 2017","subtitle":"","image":"data\/0.jpg"}]},{"code":"BCT17-7902S","name":"Tinderbox","notes":"","variant":"","file":"","id":"1815","red":"88","green":"80","blue":"77","interior":0,"product":[{"id":"100","name":"<span class='boysen-name'>BOYSEN<span class='boysen-reg'>&reg;</span><span class='boysen-reg-holder'>&reg;</span></span> Color Trend 2017","subtitle":"","image":"data\/0.jpg"}]},{"code":"BCT17-7903S","name":"Dapper Tan","notes":"","variant":"","file":"","id":"1816","red":"80","green":"76","blue":"73","interior":0,"product":[{"id":"100","name":"<span class='boysen-name'>BOYSEN<span class='boysen-reg'>&reg;</span><span class='boysen-reg-holder'>&reg;</span></span> Color Trend 2017","subtitle":"","image":"data\/0.jpg"}]},{"code":"BCT17-7904S","name":"Genuine Article","notes":"","variant":"","file":"","id":"1817","red":"53","green":"48","blue":"42","interior":0,"product":[{"id":"100","name":"<span class='boysen-name'>BOYSEN<span class='boysen-reg'>&reg;</span><span class='boysen-reg-holder'>&reg;</span></span> Color Trend 2017","subtitle":"","image":"data\/0.jpg"}]},{"code":"BCT17-7010S","name":"Crystal Sparkle","notes":"","variant":"","file":"","id":"1818","red":"214","green":"212","blue":"200","interior":0,"product":[{"id":"100","name":"<span class='boysen-name'>BOYSEN<span class='boysen-reg'>&reg;</span><span class='boysen-reg-holder'>&reg;</span></span> Color Trend 2017","subtitle":"","image":"data\/0.jpg"}]},{"code":"BCT17-7409S","name":"Pocket Rocket","notes":"","variant":"","file":"","id":"1819","red":"128","green":"188","blue":"225","interior":0,"product":[{"id":"100","name":"<span class='boysen-name'>BOYSEN<span class='boysen-reg'>&reg;</span><span class='boysen-reg-holder'>&reg;</span></span> Color Trend 2017","subtitle":"","image":"data\/0.jpg"}]},{"code":"BCT17-7410S","name":"Space Encounter","notes":"","variant":"","file":"","id":"1820","red":"120","green":"151","blue":"156","interior":0,"product":[{"id":"100","name":"<span class='boysen-name'>BOYSEN<span class='boysen-reg'>&reg;</span><span class='boysen-reg-holder'>&reg;</span></span> Color Trend 2017","subtitle":"","image":"data\/0.jpg"}]},{"code":"BCT17-7606S","name":"Glow with the Flow","notes":"","variant":"","file":"","id":"1821","red":"243","green":"212","blue":"26","interior":1,"product":[{"id":"100","name":"<span class='boysen-name'>BOYSEN<span class='boysen-reg'>&reg;</span><span class='boysen-reg-holder'>&reg;</span></span> Color Trend 2017","subtitle":"","image":"data\/0.jpg"}]},{"code":"BCT17-7716S","name":"Techy Romantic","notes":"","variant":"","file":"","id":"1822","red":"218","green":"171","blue":"153","interior":0,"product":[{"id":"100","name":"<span class='boysen-name'>BOYSEN<span class='boysen-reg'>&reg;</span><span class='boysen-reg-holder'>&reg;</span></span> Color Trend 2017","subtitle":"","image":"data\/0.jpg"}]},{"code":"BCT17-7717S","name":"Shimmer Shake","notes":"","variant":"","file":"","id":"1823","red":"237","green":"149","blue":"103","interior":0,"product":[{"id":"100","name":"<span class='boysen-name'>BOYSEN<span class='boysen-reg'>&reg;</span><span class='boysen-reg-holder'>&reg;</span></span> Color Trend 2017","subtitle":"","image":"data\/0.jpg"}]},{"code":"BCT17-7408S","name":"Tribal Teal","notes":"","variant":"","file":"","id":"1824","red":"0","green":"125","blue":"153","interior":0,"product":[{"id":"100","name":"<span class='boysen-name'>BOYSEN<span class='boysen-reg'>&reg;</span><span class='boysen-reg-holder'>&reg;</span></span> Color Trend 2017","subtitle":"","image":"data\/0.jpg"}]},{"code":"BCT17-7508S","name":"Scout's Honor","notes":"","variant":"","file":"","id":"1825","red":"0","green":"77","blue":"61","interior":0,"product":[{"id":"100","name":"<span class='boysen-name'>BOYSEN<span class='boysen-reg'>&reg;</span><span class='boysen-reg-holder'>&reg;</span></span> Color Trend 2017","subtitle":"","image":"data\/0.jpg"}]},{"code":"BCT17-7713S","name":"African Herbsman","notes":"","variant":"","file":"","id":"1826","red":"140","green":"58","blue":"72","interior":1,"product":[{"id":"100","name":"<span class='boysen-name'>BOYSEN<span class='boysen-reg'>&reg;</span><span class='boysen-reg-holder'>&reg;</span></span> Color Trend 2017","subtitle":"","image":"data\/0.jpg"}]},{"code":"BCT17-7714S","name":"Phoenician Find","notes":"","variant":"","file":"","id":"1827","red":"202","green":"139","blue":"88","interior":0,"product":[{"id":"100","name":"<span class='boysen-name'>BOYSEN<span class='boysen-reg'>&reg;</span><span class='boysen-reg-holder'>&reg;</span></span> Color Trend 2017","subtitle":"","image":"data\/0.jpg"}]},{"code":"BCT17-7715S","name":"Mystical Jar","notes":"For interior only Apply multiple coats","variant":"","file":"","id":"1828","red":"175","green":"22","blue":"42","interior":1,"product":[{"id":"100","name":"<span class='boysen-name'>BOYSEN<span class='boysen-reg'>&reg;</span><span class='boysen-reg-holder'>&reg;</span></span> Color Trend 2017","subtitle":"","image":"data\/0.jpg"}]},{"code":"BCT17-7803S","name":"Lokal Brown","notes":"","variant":"","file":"","id":"1829","red":"147","green":"117","blue":"89","interior":0,"product":[{"id":"100","name":"<span class='boysen-name'>BOYSEN<span class='boysen-reg'>&reg;</span><span class='boysen-reg-holder'>&reg;</span></span> Color Trend 2017","subtitle":"","image":"data\/0.jpg"}]},{"code":"BCT18-7013S","name":"Space Cadet","notes":"","variant":"","file":"","id":"1830","red":"190","green":"193","blue":"198","interior":0,"product":[{"id":"101","name":"<span class='boysen-name'>BOYSEN<span class='boysen-reg'>&reg;</span><span class='boysen-reg-holder'>&reg;</span></span> Color Trend 2018","subtitle":"","image":"data\/0.jpg"}]},{"code":"BCT18-7417S","name":"Green Lagoon","notes":"","variant":"","file":"","id":"1831","red":"104","green":"174","blue":"182","interior":0,"product":[{"id":"101","name":"<span class='boysen-name'>BOYSEN<span class='boysen-reg'>&reg;</span><span class='boysen-reg-holder'>&reg;</span></span> Color Trend 2018","subtitle":"","image":"data\/0.jpg"}]},{"code":"BCT18-7418S","name":"Crown Prince","notes":"","variant":"","file":"","id":"1832","red":"87","green":"89","blue":"138","interior":0,"product":[{"id":"101","name":"<span class='boysen-name'>BOYSEN<span class='boysen-reg'>&reg;</span><span class='boysen-reg-holder'>&reg;</span></span> Color Trend 2018","subtitle":"","image":"data\/0.jpg"}]},{"code":"BCT18-7608S","name":"Marquee Moon","notes":"For interior only","variant":"","file":"","id":"1833","red":"251","green":"209","blue":"61","interior":1,"product":[{"id":"101","name":"<span class='boysen-name'>BOYSEN<span class='boysen-reg'>&reg;</span><span class='boysen-reg-holder'>&reg;</span></span> Color Trend 2018","subtitle":"","image":"data\/0.jpg"}]},{"code":"BCT18-7722S","name":"Paramour","notes":"","variant":"","file":"","id":"1834","red":"227","green":"90","blue":"74","interior":0,"product":[{"id":"101","name":"<span class='boysen-name'>BOYSEN<span class='boysen-reg'>&reg;</span><span class='boysen-reg-holder'>&reg;</span></span> Color Trend 2018","subtitle":"","image":"data\/0.jpg"}]},{"code":"BCT18-7723S","name":"Pink Balloon","notes":"","variant":"","file":"","id":"1835","red":"212","green":"123","blue":"169","interior":0,"product":[{"id":"101","name":"<span class='boysen-name'>BOYSEN<span class='boysen-reg'>&reg;</span><span class='boysen-reg-holder'>&reg;</span></span> Color Trend 2018","subtitle":"","image":"data\/0.jpg"}]},{"code":"BCT18-7014S","name":"Livestream","notes":"","variant":"","file":"","id":"1836","red":"111","green":"111","blue":"99","interior":0,"product":[{"id":"101","name":"<span class='boysen-name'>BOYSEN<span class='boysen-reg'>&reg;</span><span class='boysen-reg-holder'>&reg;</span></span> Color Trend 2018","subtitle":"","image":"data\/0.jpg"}]},{"code":"BCT18-7419S","name":"Next Big Thing","notes":"","variant":"","file":"","id":"1837","red":"0","green":"56","blue":"107","interior":0,"product":[{"id":"101","name":"<span class='boysen-name'>BOYSEN<span class='boysen-reg'>&reg;</span><span class='boysen-reg-holder'>&reg;</span></span> Color Trend 2018","subtitle":"","image":"data\/0.jpg"}]},{"code":"BCT18-7420S","name":"Silicon Start-Up","notes":"","variant":"","file":"","id":"1838","red":"0","green":"150","blue":"203","interior":0,"product":[{"id":"101","name":"<span class='boysen-name'>BOYSEN<span class='boysen-reg'>&reg;</span><span class='boysen-reg-holder'>&reg;</span></span> Color Trend 2018","subtitle":"","image":"data\/0.jpg"}]},{"code":"BCT18-7421S","name":"Movie Night","notes":"","variant":"","file":"","id":"1839","red":"66","green":"79","blue":"95","interior":0,"product":[{"id":"101","name":"<span class='boysen-name'>BOYSEN<span class='boysen-reg'>&reg;</span><span class='boysen-reg-holder'>&reg;</span></span> Color Trend 2018","subtitle":"","image":"data\/0.jpg"}]},{"code":"BCT18-7609S","name":"Work From Home","notes":"","variant":"","file":"","id":"1840","red":"230","green":"202","blue":"154","interior":0,"product":[{"id":"101","name":"<span class='boysen-name'>BOYSEN<span class='boysen-reg'>&reg;</span><span class='boysen-reg-holder'>&reg;</span></span> Color Trend 2018","subtitle":"","image":"data\/0.jpg"}]},{"code":"BCT18-7724S","name":"Hot Rod","notes":"","variant":"","file":"","id":"1841","red":"197","green":"35","blue":"22","interior":1,"product":[{"id":"101","name":"<span class='boysen-name'>BOYSEN<span class='boysen-reg'>&reg;</span><span class='boysen-reg-holder'>&reg;</span></span> Color Trend 2018","subtitle":"","image":"data\/0.jpg"}]},{"code":"BCT18-7204S","name":"Marble Chalk","notes":"","variant":"","file":"","id":"1842","red":"197","green":"204","blue":"186","interior":0,"product":[{"id":"101","name":"<span class='boysen-name'>BOYSEN<span class='boysen-reg'>&reg;</span><span class='boysen-reg-holder'>&reg;</span></span> Color Trend 2018","subtitle":"","image":"data\/0.jpg"}]},{"code":"BCT18-7414S","name":"Root Crop","notes":"","variant":"","file":"","id":"1843","red":"80","green":"66","blue":"89","interior":0,"product":[{"id":"101","name":"<span class='boysen-name'>BOYSEN<span class='boysen-reg'>&reg;</span><span class='boysen-reg-holder'>&reg;</span></span> Color Trend 2018","subtitle":"","image":"data\/0.jpg"}]},{"code":"BCT18-7510S","name":"Forest Ranger","notes":"","variant":"","file":"","id":"1844","red":"0","green":"77","blue":"77","interior":0,"product":[{"id":"101","name":"<span class='boysen-name'>BOYSEN<span class='boysen-reg'>&reg;</span><span class='boysen-reg-holder'>&reg;</span></span> Color Trend 2018","subtitle":"","image":"data\/0.jpg"}]},{"code":"BCT18-7805S","name":"Gypsy Train","notes":"","variant":"","file":"","id":"1845","red":"109","green":"88","blue":"93","interior":0,"product":[{"id":"101","name":"<span class='boysen-name'>BOYSEN<span class='boysen-reg'>&reg;</span><span class='boysen-reg-holder'>&reg;</span></span> Color Trend 2018","subtitle":"","image":"data\/0.jpg"}]},{"code":"BCT18-7607S","name":"Yellowstone Park","notes":"","variant":"","file":"","id":"1846","red":"204","green":"160","blue":"12","interior":1,"product":[{"id":"101","name":"<span class='boysen-name'>BOYSEN<span class='boysen-reg'>&reg;</span><span class='boysen-reg-holder'>&reg;</span></span> Color Trend 2018","subtitle":"","image":"data\/0.jpg"}]},{"code":"BCT18-7905S","name":"Night Watch","notes":"","variant":"","file":"","id":"1847","red":"50","green":"51","blue":"53","interior":0,"product":[{"id":"101","name":"<span class='boysen-name'>BOYSEN<span class='boysen-reg'>&reg;</span><span class='boysen-reg-holder'>&reg;</span></span> Color Trend 2018","subtitle":"","image":"data\/0.jpg"}]},{"code":"BCT18-7011S","name":"Private Stock","notes":"","variant":"","file":"","id":"1848","red":"183","green":"183","blue":"175","interior":0,"product":[{"id":"101","name":"<span class='boysen-name'>BOYSEN<span class='boysen-reg'>&reg;</span><span class='boysen-reg-holder'>&reg;</span></span> Color Trend 2018","subtitle":"","image":"data\/0.jpg"}]},{"code":"BCT18-7012S","name":"Bluegrass Suite","notes":"","variant":"","file":"","id":"1849","red":"165","green":"192","blue":"185","interior":0,"product":[{"id":"101","name":"<span class='boysen-name'>BOYSEN<span class='boysen-reg'>&reg;</span><span class='boysen-reg-holder'>&reg;</span></span> Color Trend 2018","subtitle":"","image":"data\/0.jpg"}]},{"code":"BCT18-7205S","name":"Skin Is In","notes":"","variant":"","file":"","id":"1850","red":"220","green":"200","blue":"191","interior":0,"product":[{"id":"101","name":"<span class='boysen-name'>BOYSEN<span class='boysen-reg'>&reg;</span><span class='boysen-reg-holder'>&reg;</span></span> Color Trend 2018","subtitle":"","image":"data\/0.jpg"}]},{"code":"BCT18-7415S","name":"Blue For You","notes":"","variant":"","file":"","id":"1851","red":"0","green":"112","blue":"186","interior":0,"product":[{"id":"101","name":"<span class='boysen-name'>BOYSEN<span class='boysen-reg'>&reg;</span><span class='boysen-reg-holder'>&reg;</span></span> Color Trend 2018","subtitle":"","image":"data\/0.jpg"}]},{"code":"BCT18-7416S","name":"New Breed","notes":"","variant":"","file":"","id":"1852","red":"56","green":"76","blue":"109","interior":0,"product":[{"id":"101","name":"<span class='boysen-name'>BOYSEN<span class='boysen-reg'>&reg;</span><span class='boysen-reg-holder'>&reg;</span></span> Color Trend 2018","subtitle":"","image":"data\/0.jpg"}]},{"code":"BCT18-7806S","name":"Strange Brew","notes":"","variant":"","file":"","id":"1853","red":"159","green":"130","blue":"122","interior":0,"product":[{"id":"101","name":"<span class='boysen-name'>BOYSEN<span class='boysen-reg'>&reg;</span><span class='boysen-reg-holder'>&reg;</span></span> Color Trend 2018","subtitle":"","image":"data\/0.jpg"}]},{"code":"B&#8209;752","name":"Mystery Winter","notes":"","variant":"","file":"","id":"1854","red":"141","green":"165","blue":"143","interior":0,"product":[{"id":"54","name":"<span class='boysen-name'>BOYSEN<span class='boysen-reg'>&reg;</span><span class='boysen-reg-holder'>&reg;</span></span> Permacoat&trade; Latex","subtitle":"","image":"data\/0.jpg"},{"id":"94","name":"<span class='boysen-name'>BOYSEN<span class='boysen-reg'>&reg;</span><span class='boysen-reg-holder'>&reg;</span></span> Colorizer Series G","subtitle":"","image":"data\/0.jpg"}]},{"code":"BSC-44","name":"Dusty Beige","notes":"","variant":"","file":"","id":"1855","red":"203","green":"190","blue":"171","interior":0,"product":[{"id":"94","name":"<span class='boysen-name'>BOYSEN<span class='boysen-reg'>&reg;</span><span class='boysen-reg-holder'>&reg;</span></span> Colorizer Series G","subtitle":"","image":"data\/0.jpg"}]},{"code":"BSG-2","name":"Snow Field","notes":"","variant":"","file":"","id":"1856","red":"223","green":"219","blue":"216","interior":0,"product":[{"id":"94","name":"<span class='boysen-name'>BOYSEN<span class='boysen-reg'>&reg;</span><span class='boysen-reg-holder'>&reg;</span></span> Colorizer Series G","subtitle":"","image":"data\/0.jpg"}]},{"code":"BSG-5","name":"Mist","notes":"","variant":"","file":"","id":"1857","red":"222","green":"213","blue":"198","interior":0,"product":[{"id":"94","name":"<span class='boysen-name'>BOYSEN<span class='boysen-reg'>&reg;</span><span class='boysen-reg-holder'>&reg;</span></span> Colorizer Series G","subtitle":"","image":"data\/0.jpg"}]},{"code":"BSG-6","name":"Stone Ware","notes":"","variant":"","file":"","id":"1858","red":"226","green":"216","blue":"204","interior":0,"product":[{"id":"94","name":"<span class='boysen-name'>BOYSEN<span class='boysen-reg'>&reg;</span><span class='boysen-reg-holder'>&reg;</span></span> Colorizer Series G","subtitle":"","image":"data\/0.jpg"}]},{"code":"BSG-7","name":"Soapstone","notes":"","variant":"","file":"","id":"1859","red":"213","green":"207","blue":"195","interior":0,"product":[{"id":"94","name":"<span class='boysen-name'>BOYSEN<span class='boysen-reg'>&reg;</span><span class='boysen-reg-holder'>&reg;</span></span> Colorizer Series G","subtitle":"","image":"data\/0.jpg"}]},{"code":"BSG-8","name":"Grey Rock Inn","notes":"","variant":"","file":"","id":"1860","red":"203","green":"199","blue":"187","interior":0,"product":[{"id":"94","name":"<span class='boysen-name'>BOYSEN<span class='boysen-reg'>&reg;</span><span class='boysen-reg-holder'>&reg;</span></span> Colorizer Series G","subtitle":"","image":"data\/0.jpg"}]},{"code":"BSG-10","name":"Cloud White","notes":"","variant":"","file":"","id":"1861","red":"225","green":"218","blue":"202","interior":0,"product":[{"id":"94","name":"<span class='boysen-name'>BOYSEN<span class='boysen-reg'>&reg;</span><span class='boysen-reg-holder'>&reg;</span></span> Colorizer Series G","subtitle":"","image":"data\/0.jpg"}]},{"code":"BSG-12","name":"Shaded Ice","notes":"","variant":"","file":"","id":"1862","red":"217","green":"218","blue":"220","interior":0,"product":[{"id":"94","name":"<span class='boysen-name'>BOYSEN<span class='boysen-reg'>&reg;</span><span class='boysen-reg-holder'>&reg;</span></span> Colorizer Series G","subtitle":"","image":"data\/0.jpg"}]},{"code":"BSG-13","name":"Grey Facade","notes":"","variant":"","file":"","id":"1863","red":"199","green":"197","blue":"202","interior":0,"product":[{"id":"94","name":"<span class='boysen-name'>BOYSEN<span class='boysen-reg'>&reg;</span><span class='boysen-reg-holder'>&reg;</span></span> Colorizer Series G","subtitle":"","image":"data\/0.jpg"}]},{"code":"BSG-14","name":"Rain Cloud","notes":"","variant":"","file":"","id":"1864","red":"206","green":"198","blue":"187","interior":0,"product":[{"id":"94","name":"<span class='boysen-name'>BOYSEN<span class='boysen-reg'>&reg;</span><span class='boysen-reg-holder'>&reg;</span></span> Colorizer Series G","subtitle":"","image":"data\/0.jpg"}]},{"code":"BSG-18","name":"Brown Pony","notes":"","variant":"","file":"","id":"1865","red":"185","green":"170","blue":"163","interior":0,"product":[{"id":"94","name":"<span class='boysen-name'>BOYSEN<span class='boysen-reg'>&reg;</span><span class='boysen-reg-holder'>&reg;</span></span> Colorizer Series G","subtitle":"","image":"data\/0.jpg"}]},{"code":"BSG-20","name":"Sun City","notes":"","variant":"","file":"","id":"1866","red":"209","green":"186","blue":"142","interior":0,"product":[{"id":"94","name":"<span class='boysen-name'>BOYSEN<span class='boysen-reg'>&reg;</span><span class='boysen-reg-holder'>&reg;</span></span> Colorizer Series G","subtitle":"","image":"data\/0.jpg"}]},{"code":"BSG-21","name":"Tantalizing Tan","notes":"","variant":"","file":"","id":"1867","red":"194","green":"166","blue":"142","interior":0,"product":[{"id":"94","name":"<span class='boysen-name'>BOYSEN<span class='boysen-reg'>&reg;</span><span class='boysen-reg-holder'>&reg;</span></span> Colorizer Series G","subtitle":"","image":"data\/0.jpg"}]},{"code":"BSG-22","name":"Front Porch","notes":"","variant":"","file":"","id":"1868","red":"187","green":"177","blue":"168","interior":0,"product":[{"id":"94","name":"<span class='boysen-name'>BOYSEN<span class='boysen-reg'>&reg;</span><span class='boysen-reg-holder'>&reg;</span></span> Colorizer Series G","subtitle":"","image":"data\/0.jpg"}]},{"code":"BSG-23","name":"Thunder Cloud","notes":"","variant":"","file":"","id":"1869","red":"183","green":"177","blue":"165","interior":0,"product":[{"id":"94","name":"<span class='boysen-name'>BOYSEN<span class='boysen-reg'>&reg;</span><span class='boysen-reg-holder'>&reg;</span></span> Colorizer Series G","subtitle":"","image":"data\/0.jpg"}]},{"code":"BSG-24","name":"Mud Pie","notes":"","variant":"","file":"","id":"1870","red":"141","green":"131","blue":"121","interior":0,"product":[{"id":"94","name":"<span class='boysen-name'>BOYSEN<span class='boysen-reg'>&reg;</span><span class='boysen-reg-holder'>&reg;</span></span> Colorizer Series G","subtitle":"","image":"data\/0.jpg"}]},{"code":"BSG-26","name":"Gray Tropics","notes":"","variant":"","file":"","id":"1871","red":"187","green":"187","blue":"187","interior":0,"product":[{"id":"94","name":"<span class='boysen-name'>BOYSEN<span class='boysen-reg'>&reg;</span><span class='boysen-reg-holder'>&reg;</span></span> Colorizer Series G","subtitle":"","image":"data\/0.jpg"}]},{"code":"BSG-27","name":"Granite","notes":"","variant":"","file":"","id":"1872","red":"173","green":"175","blue":"174","interior":0,"product":[{"id":"94","name":"<span class='boysen-name'>BOYSEN<span class='boysen-reg'>&reg;</span><span class='boysen-reg-holder'>&reg;</span></span> Colorizer Series G","subtitle":"","image":"data\/0.jpg"}]},{"code":"BSG-28","name":"Melted Ice","notes":"","variant":"","file":"","id":"1873","red":"174","green":"185","blue":"189","interior":0,"product":[{"id":"94","name":"<span class='boysen-name'>BOYSEN<span class='boysen-reg'>&reg;</span><span class='boysen-reg-holder'>&reg;</span></span> Colorizer Series G","subtitle":"","image":"data\/0.jpg"}]},{"code":"BSG-29","name":"French Silver","notes":"","variant":"","file":"","id":"1874","red":"164","green":"180","blue":"193","interior":0,"product":[{"id":"94","name":"<span class='boysen-name'>BOYSEN<span class='boysen-reg'>&reg;</span><span class='boysen-reg-holder'>&reg;</span></span> Colorizer Series G","subtitle":"","image":"data\/0.jpg"}]},{"code":"BSG-30","name":"Dresden Dream","notes":"","variant":"","file":"","id":"1875","red":"137","green":"144","blue":"162","interior":0,"product":[{"id":"94","name":"<span class='boysen-name'>BOYSEN<span class='boysen-reg'>&reg;</span><span class='boysen-reg-holder'>&reg;</span></span> Colorizer Series G","subtitle":"","image":"data\/0.jpg"}]},{"code":"BSG-32","name":"Slate Gray","notes":"","variant":"","file":"","id":"1876","red":"142","green":"153","blue":"159","interior":0,"product":[{"id":"94","name":"<span class='boysen-name'>BOYSEN<span class='boysen-reg'>&reg;</span><span class='boysen-reg-holder'>&reg;</span></span> Colorizer Series G","subtitle":"","image":"data\/0.jpg"}]},{"code":"BSG-33","name":"Hillside View","notes":"","variant":"","file":"","id":"1877","red":"146","green":"167","blue":"170","interior":0,"product":[{"id":"94","name":"<span class='boysen-name'>BOYSEN<span class='boysen-reg'>&reg;</span><span class='boysen-reg-holder'>&reg;</span></span> Colorizer Series G","subtitle":"","image":"data\/0.jpg"}]},{"code":"BSG-34","name":"Silvery Moonlight","notes":"","variant":"","file":"","id":"1878","red":"199","green":"208","blue":"207","interior":0,"product":[{"id":"94","name":"<span class='boysen-name'>BOYSEN<span class='boysen-reg'>&reg;</span><span class='boysen-reg-holder'>&reg;</span></span> Colorizer Series G","subtitle":"","image":"data\/0.jpg"}]},{"code":"BSG-35","name":"Autumn Mist","notes":"","variant":"","file":"","id":"1879","red":"197","green":"209","blue":"207","interior":0,"product":[{"id":"94","name":"<span class='boysen-name'>BOYSEN<span class='boysen-reg'>&reg;</span><span class='boysen-reg-holder'>&reg;</span></span> Colorizer Series G","subtitle":"","image":"data\/0.jpg"}]},{"code":"BSG-37","name":"Windward","notes":"","variant":"","file":"","id":"1880","red":"109","green":"190","blue":"183","interior":0,"product":[{"id":"94","name":"<span class='boysen-name'>BOYSEN<span class='boysen-reg'>&reg;</span><span class='boysen-reg-holder'>&reg;</span></span> Colorizer Series G","subtitle":"","image":"data\/0.jpg"}]},{"code":"BSG-38","name":"Winter Rain","notes":"","variant":"","file":"","id":"1881","red":"177","green":"210","blue":"217","interior":0,"product":[{"id":"94","name":"<span class='boysen-name'>BOYSEN<span class='boysen-reg'>&reg;</span><span class='boysen-reg-holder'>&reg;</span></span> Colorizer Series G","subtitle":"","image":"data\/0.jpg"}]},{"code":"BSG-39","name":"Green Gage","notes":"","variant":"","file":"","id":"1882","red":"191","green":"188","blue":"133","interior":0,"product":[{"id":"94","name":"<span class='boysen-name'>BOYSEN<span class='boysen-reg'>&reg;</span><span class='boysen-reg-holder'>&reg;</span></span> Colorizer Series G","subtitle":"","image":"data\/0.jpg"}]},{"code":"BSG-40","name":"Spring Fest","notes":"","variant":"","file":"","id":"1883","red":"182","green":"223","blue":"157","interior":0,"product":[{"id":"94","name":"<span class='boysen-name'>BOYSEN<span class='boysen-reg'>&reg;</span><span class='boysen-reg-holder'>&reg;</span></span> Colorizer Series G","subtitle":"","image":"data\/0.jpg"}]},{"code":"BSG-41","name":"Quaking Grass","notes":"","variant":"","file":"","id":"1884","red":"130","green":"170","blue":"120","interior":0,"product":[{"id":"94","name":"<span class='boysen-name'>BOYSEN<span class='boysen-reg'>&reg;</span><span class='boysen-reg-holder'>&reg;</span></span> Colorizer Series G","subtitle":"","image":"data\/0.jpg"}]},{"code":"BSG-44","name":"Pine Grove","notes":"","variant":"","file":"","id":"1885","red":"75","green":"133","blue":"108","interior":0,"product":[{"id":"94","name":"<span class='boysen-name'>BOYSEN<span class='boysen-reg'>&reg;</span><span class='boysen-reg-holder'>&reg;</span></span> Colorizer Series G","subtitle":"","image":"data\/0.jpg"}]},{"code":"BSG-45","name":"Malachite","notes":"","variant":"","file":"","id":"1886","red":"84","green":"112","blue":"100","interior":0,"product":[{"id":"94","name":"<span class='boysen-name'>BOYSEN<span class='boysen-reg'>&reg;</span><span class='boysen-reg-holder'>&reg;</span></span> Colorizer Series G","subtitle":"","image":"data\/0.jpg"}]},{"code":"BSG-47","name":"Tall Evergreen","notes":"","variant":"","file":"","id":"1887","red":"32","green":"78","blue":"67","interior":0,"product":[{"id":"94","name":"<span class='boysen-name'>BOYSEN<span class='boysen-reg'>&reg;</span><span class='boysen-reg-holder'>&reg;</span></span> Colorizer Series G","subtitle":"","image":"data\/0.jpg"}]},{"code":"BSG-48","name":"Forest Charcoal","notes":"","variant":"","file":"","id":"1888","red":"52","green":"96","blue":"99","interior":0,"product":[{"id":"94","name":"<span class='boysen-name'>BOYSEN<span class='boysen-reg'>&reg;</span><span class='boysen-reg-holder'>&reg;</span></span> Colorizer Series G","subtitle":"","image":"data\/0.jpg"}]},{"code":"BSG-50","name":"Pacific Heights","notes":"","variant":"","file":"","id":"1889","red":"130","green":"175","blue":"178","interior":0,"product":[{"id":"94","name":"<span class='boysen-name'>BOYSEN<span class='boysen-reg'>&reg;</span><span class='boysen-reg-holder'>&reg;</span></span> Colorizer Series G","subtitle":"","image":"data\/0.jpg"}]},{"code":"BSG-51","name":"Java Sea","notes":"","variant":"","file":"","id":"1890","red":"0","green":"153","blue":"171","interior":0,"product":[{"id":"94","name":"<span class='boysen-name'>BOYSEN<span class='boysen-reg'>&reg;</span><span class='boysen-reg-holder'>&reg;</span></span> Colorizer Series G","subtitle":"","image":"data\/0.jpg"}]},{"code":"BSG-52","name":"Moonglow","notes":"","variant":"","file":"","id":"1891","red":"118","green":"200","blue":"211","interior":0,"product":[{"id":"94","name":"<span class='boysen-name'>BOYSEN<span class='boysen-reg'>&reg;</span><span class='boysen-reg-holder'>&reg;</span></span> Colorizer Series G","subtitle":"","image":"data\/0.jpg"}]},{"code":"BSG-53","name":"Brussels Blue","notes":"","variant":"","file":"","id":"1892","red":"152","green":"200","blue":"220","interior":0,"product":[{"id":"94","name":"<span class='boysen-name'>BOYSEN<span class='boysen-reg'>&reg;</span><span class='boysen-reg-holder'>&reg;</span></span> Colorizer Series G","subtitle":"","image":"data\/0.jpg"}]},{"code":"BSG-54","name":"Pale Blue","notes":"","variant":"","file":"","id":"1893","red":"151","green":"187","blue":"221","interior":0,"product":[{"id":"94","name":"<span class='boysen-name'>BOYSEN<span class='boysen-reg'>&reg;</span><span class='boysen-reg-holder'>&reg;</span></span> Colorizer Series G","subtitle":"","image":"data\/0.jpg"}]},{"code":"BSG-55","name":"Tranquil Blue","notes":"","variant":"","file":"","id":"1894","red":"152","green":"186","blue":"213","interior":0,"product":[{"id":"94","name":"<span class='boysen-name'>BOYSEN<span class='boysen-reg'>&reg;</span><span class='boysen-reg-holder'>&reg;</span></span> Colorizer Series G","subtitle":"","image":"data\/0.jpg"}]},{"code":"BSG-58","name":"Fine China","notes":"","variant":"","file":"","id":"1895","red":"141","green":"144","blue":"161","interior":0,"product":[{"id":"94","name":"<span class='boysen-name'>BOYSEN<span class='boysen-reg'>&reg;</span><span class='boysen-reg-holder'>&reg;</span></span> Colorizer Series G","subtitle":"","image":"data\/0.jpg"}]},{"code":"BSG-59","name":"Eagle Cliff","notes":"","variant":"","file":"","id":"1896","red":"188","green":"178","blue":"186","interior":0,"product":[{"id":"94","name":"<span class='boysen-name'>BOYSEN<span class='boysen-reg'>&reg;</span><span class='boysen-reg-holder'>&reg;</span></span> Colorizer Series G","subtitle":"","image":"data\/0.jpg"}]},{"code":"BSG-60","name":"Spacious Luxury","notes":"","variant":"","file":"","id":"1897","red":"210","green":"203","blue":"219","interior":0,"product":[{"id":"94","name":"<span class='boysen-name'>BOYSEN<span class='boysen-reg'>&reg;</span><span class='boysen-reg-holder'>&reg;</span></span> Colorizer Series G","subtitle":"","image":"data\/0.jpg"}]},{"code":"BSG-61","name":"Rising Violet","notes":"","variant":"","file":"","id":"1898","red":"209","green":"187","blue":"200","interior":0,"product":[{"id":"94","name":"<span class='boysen-name'>BOYSEN<span class='boysen-reg'>&reg;</span><span class='boysen-reg-holder'>&reg;</span></span> Colorizer Series G","subtitle":"","image":"data\/0.jpg"}]},{"code":"BSG-62","name":"Sand Coral","notes":"","variant":"","file":"","id":"1899","red":"208","green":"172","blue":"176","interior":0,"product":[{"id":"94","name":"<span class='boysen-name'>BOYSEN<span class='boysen-reg'>&reg;</span><span class='boysen-reg-holder'>&reg;</span></span> Colorizer Series G","subtitle":"","image":"data\/0.jpg"}]}]