[{"code":"B&#8209;8580","name":"Zen Brown","headerimageurl":"","variant":"","file":"","imageurl":"","id":"79","red":"62","green":"38","blue":"37","interior":"0","available":"1"},{"code":"B&#8209;4780","name":"Brown","variant":"1 Toner","file":"data\/2088.jpg","imageurl":"https:\/\/files.boysencdn.com\/boysen\/uploads\/color\/full\/2088.jpg","id":"88","red":"-1","green":"-1","blue":"-1","interior":"0","available":"1"},{"code":"B&#8209;4780","name":"Brown","variant":"1\/2 Toner","file":"data\/2097.jpg","imageurl":"https:\/\/files.boysencdn.com\/boysen\/uploads\/color\/full\/2097.jpg","id":"97","red":"-1","green":"-1","blue":"-1","interior":"0","available":"1"},{"code":"B&#8209;4780","name":"Brown","headerimageurl":"","variant":"1\/4 Toner","file":"data\/2106.jpg","imageurl":"https:\/\/files.boysencdn.com\/boysen\/uploads\/color\/full\/2106.jpg","id":"106","red":"-1","green":"-1","blue":"-1","interior":"0","available":"1"},{"code":"B&#8209;4780","name":"Brown","variant":"1 Toner","file":"data\/2088.jpg","imageurl":"https:\/\/files.boysencdn.com\/boysen\/uploads\/color\/full\/2088.jpg","id":"88","red":"-1","green":"-1","blue":"-1","interior":"0","available":"1"},{"code":"B&#8209;4780","name":"Brown","variant":"1\/2 Toner","file":"data\/2097.jpg","imageurl":"https:\/\/files.boysencdn.com\/boysen\/uploads\/color\/full\/2097.jpg","id":"97","red":"-1","green":"-1","blue":"-1","interior":"0","available":"1"},{"code":"B&#8209;4780","name":"Brown","headerimageurl":"","variant":"1\/4 Toner","file":"data\/2106.jpg","imageurl":"https:\/\/files.boysencdn.com\/boysen\/uploads\/color\/full\/2106.jpg","id":"106","red":"-1","green":"-1","blue":"-1","interior":"0","available":"1"},{"code":"B&#8209;4780","name":"Brown","variant":"1 Toner","file":"data\/2088.jpg","imageurl":"https:\/\/files.boysencdn.com\/boysen\/uploads\/color\/full\/2088.jpg","id":"88","red":"-1","green":"-1","blue":"-1","interior":"0","available":"1"},{"code":"B&#8209;4780","name":"Brown","variant":"1\/2 Toner","file":"data\/2097.jpg","imageurl":"https:\/\/files.boysencdn.com\/boysen\/uploads\/color\/full\/2097.jpg","id":"97","red":"-1","green":"-1","blue":"-1","interior":"0","available":"1"},{"code":"B&#8209;4780","name":"Brown","headerimageurl":"","variant":"1\/4 Toner","file":"data\/2106.jpg","imageurl":"https:\/\/files.boysencdn.com\/boysen\/uploads\/color\/full\/2106.jpg","id":"106","red":"-1","green":"-1","blue":"-1","interior":"0","available":"1"},{"code":"HH-780","name":"Chocolate Brown","headerimageurl":"","variant":"","file":"","imageurl":"","id":"125","red":"87","green":"76","blue":"74","interior":"0","available":"1"},{"code":"BSGV1-101","name":"Chocolate Brown","headerimageurl":"","variant":"","file":"","imageurl":"","id":"161","red":"92","green":"82","blue":"77","interior":"0","available":"0"},{"code":"B&#8209;680","name":"Chocolate Brown","headerimageurl":"","variant":"","file":"","imageurl":"","id":"251","red":"54","green":"37","blue":"35","interior":"0","available":"1"},{"code":"B&#8209;683","name":"Caramel Brown","headerimageurl":"","variant":"","file":"","imageurl":"","id":"253","red":"118","green":"75","blue":"59","interior":"0","available":"1"},{"code":"B&#8209;685","name":"Sammy Brown","headerimageurl":"","variant":"","file":"","imageurl":"","id":"254","red":"94","green":"81","blue":"62","interior":"0","available":"1"},{"code":"B&#8209;2580","name":"Chocolate Brown","headerimageurl":"","variant":"","file":"","imageurl":"","id":"262","red":"65","green":"45","blue":"45","interior":"0","available":"1"},{"code":"NS-1571","name":"Terra Cotta","headerimageurl":"","variant":"","file":"","imageurl":"","id":"271","red":"136","green":"39","blue":"20","interior":"0","available":"1"},{"code":"NS-983","name":"Caramel Brown","headerimageurl":"","variant":"","file":"","imageurl":"","id":"281","red":"113","green":"66","blue":"38","interior":"0","available":"1"},{"code":"T-5800","name":"Choco Brown","headerimageurl":"","variant":"","file":"","imageurl":"","id":"326","red":"90","green":"80","blue":"75","interior":"0","available":"1"},{"code":"T-5804","name":"Burger Brown","headerimageurl":"","variant":"","file":"","imageurl":"","id":"329","red":"156","green":"117","blue":"99","interior":"0","available":"1"},{"code":"V-9000C76","name":"Passion","headerimageurl":"","variant":"","file":"","imageurl":"","id":"386","red":"140","green":"61","blue":"60","interior":"0","available":"1"},{"code":"B&#8209;5083","name":"Brown","headerimageurl":"","variant":"","file":"","imageurl":"","id":"402","red":"-1","green":"-1","blue":"-1","interior":"0","available":"1"},{"code":"832","name":"Light Brown\n(24 kg B&#8209;5010 <span class='boysen-name'>BOYSEN<span class='boysen-reg'>&reg;</span><span class='boysen-reg-holder'>&reg;</span></span> Marmorino&trade; Classico + 240g B&#8209;5083 <span class='boysen-name'>BOYSEN<span class='boysen-reg'>&reg;</span><span class='boysen-reg-holder'>&reg;</span></span> Marmorino&trade; Brown Toner)","headerimageurl":"","variant":"","file":"data\/2418.jpg","imageurl":"https:\/\/files.boysencdn.com\/boysen\/uploads\/color\/full\/2418.jpg","id":"418","red":"-1","green":"-1","blue":"-1","interior":"0","available":"1"},{"code":"833","name":"Medium Brown\n(24 kg B&#8209;5010 <span class='boysen-name'>BOYSEN<span class='boysen-reg'>&reg;</span><span class='boysen-reg-holder'>&reg;</span></span> Marmorino&trade; Classico + 729g B&#8209;5083 <span class='boysen-name'>BOYSEN<span class='boysen-reg'>&reg;</span><span class='boysen-reg-holder'>&reg;</span></span> Marmorino&trade; Brown Toner)","headerimageurl":"","variant":"","file":"data\/2419.jpg","imageurl":"https:\/\/files.boysencdn.com\/boysen\/uploads\/color\/full\/2419.jpg","id":"419","red":"-1","green":"-1","blue":"-1","interior":"0","available":"1"},{"code":"834","name":"Dark Brown\n(24 kg B&#8209;5010 <span class='boysen-name'>BOYSEN<span class='boysen-reg'>&reg;</span><span class='boysen-reg-holder'>&reg;</span></span> Marmorino&trade; Classico + 1680g B&#8209;5083 <span class='boysen-name'>BOYSEN<span class='boysen-reg'>&reg;</span><span class='boysen-reg-holder'>&reg;</span></span> Marmorino&trade; Brown Toner)","headerimageurl":"","variant":"","file":"data\/2420.jpg","imageurl":"https:\/\/files.boysencdn.com\/boysen\/uploads\/color\/full\/2420.jpg","id":"420","red":"-1","green":"-1","blue":"-1","interior":"0","available":"1"},{"code":"BCP-0046","name":"Valentino","headerimageurl":"","variant":"","file":"","imageurl":"","id":"477","red":"125","green":"75","blue":"62","interior":"0","available":"0"},{"code":"BCP-0053","name":"Remaining Embers","headerimageurl":"","variant":"","file":"","imageurl":"","id":"484","red":"135","green":"78","blue":"60","interior":"0","available":"0"},{"code":"BCP-0059","name":"Quintessential","headerimageurl":"","variant":"","file":"","imageurl":"","id":"490","red":"136","green":"80","blue":"71","interior":"0","available":"0"},{"code":"BCP-0121","name":"Savanna","headerimageurl":"","variant":"","file":"","imageurl":"","id":"552","red":"129","green":"74","blue":"66","interior":"0","available":"0"},{"code":"BCP-0122","name":"Outrageous","headerimageurl":"","variant":"","file":"","imageurl":"","id":"553","red":"124","green":"67","blue":"54","interior":"0","available":"0"},{"code":"BCP-0123","name":"Monterey Chestnut","headerimageurl":"","variant":"","file":"","imageurl":"","id":"554","red":"119","green":"65","blue":"51","interior":"0","available":"0"},{"code":"BCP-0184","name":"Macadamia Brown","headerimageurl":"","variant":"","file":"","imageurl":"","id":"615","red":"182","green":"161","blue":"141","interior":"0","available":"0"},{"code":"BCP-0221","name":"Brown Suede","headerimageurl":"","variant":"","file":"","imageurl":"","id":"652","red":"93","green":"81","blue":"69","interior":"0","available":"0"},{"code":"BCP-0260","name":"Cocoa Nib","headerimageurl":"","variant":"","file":"","imageurl":"","id":"691","red":"186","green":"155","blue":"124","interior":"0","available":"0"},{"code":"BCP-0795","name":"Martina Olive\n*For interior only","headerimageurl":"","variant":"","file":"","imageurl":"","id":"1226","red":"145","green":"136","blue":"62","interior":"1","available":"0"},{"code":"BCP-1040","name":"Dark Marmalade","headerimageurl":"","variant":"","file":"","imageurl":"","id":"1471","red":"148","green":"75","blue":"62","interior":"0","available":"0"},{"code":"BCP-1061","name":"April Love","headerimageurl":"","variant":"","file":"","imageurl":"","id":"1492","red":"136","green":"68","blue":"55","interior":"0","available":"0"},{"code":"BCT14-7505S","name":"Granny Orchard\n*For interior only","headerimageurl":"","variant":"","file":"","imageurl":"","id":"1767","red":"146","green":"144","blue":"80","interior":"1","available":"0"},{"code":"BCT14-7704S","name":"Thimbleberry\n*For interior only","headerimageurl":"","variant":"","file":"","imageurl":"","id":"1768","red":"133","green":"60","blue":"50","interior":"1","available":"0"},{"code":"BCT17-7803S","name":"Lokal Brown","headerimageurl":"","variant":"","file":"","imageurl":"","id":"1829","red":"139","green":"118","blue":"94","interior":"0","available":"0"},{"code":"BSGV1-102","name":"Brown Pony","headerimageurl":"","variant":"","file":"","imageurl":"","id":"1865","red":"182","green":"166","blue":"161","interior":"0","available":"0"},{"code":"HH-40-G66","name":"Cocoa Butter","headerimageurl":"","variant":"","file":"","imageurl":"","id":"2056","red":"120","green":"95","blue":"79","interior":"0","available":"0"},{"code":"BM-0025","name":"Simply Brown","headerimageurl":"","variant":"","file":"","imageurl":"","id":"2081","red":"122","green":"103","blue":"98","interior":"0","available":"0"},{"code":"BM-0054","name":"Brown Ben","headerimageurl":"","variant":"","file":"","imageurl":"","id":"2110","red":"150","green":"105","blue":"82","interior":"0","available":"0"},{"code":"BM-0200","name":"Elegant Brown","headerimageurl":"","variant":"","file":"","imageurl":"","id":"2256","red":"120","green":"109","blue":"111","interior":"0","available":"0"},{"code":"V-243","name":"Manhattan Brown","headerimageurl":"","variant":"","file":"","imageurl":"","id":"2572","red":"224","green":"134","blue":"82","interior":"0","available":"0"},{"code":"V-352","name":"Burgundy Locks","headerimageurl":"","variant":"","file":"","imageurl":"","id":"2681","red":"139","green":"82","blue":"71","interior":"0","available":"0"},{"code":"V-362","name":"Sandy Brown","headerimageurl":"","variant":"","file":"","imageurl":"","id":"2691","red":"242","green":"192","blue":"157","interior":"0","available":"0"},{"code":"V-364","name":"Chippendale Brown","headerimageurl":"","variant":"","file":"","imageurl":"","id":"2693","red":"169","green":"93","blue":"61","interior":"0","available":"0"},{"code":"V-368","name":"Mahogany","headerimageurl":"","variant":"","file":"","imageurl":"","id":"2697","red":"136","green":"85","blue":"56","interior":"0","available":"0"},{"code":"V-375","name":"Exotic Brown","headerimageurl":"","variant":"","file":"","imageurl":"","id":"2704","red":"197","green":"147","blue":"106","interior":"0","available":"1"},{"code":"V-381","name":"Flax Brown","headerimageurl":"","variant":"","file":"","imageurl":"","id":"2710","red":"242","green":"209","blue":"164","interior":"0","available":"0"},{"code":"V-387","name":"Capiya Brown","headerimageurl":"","variant":"","file":"","imageurl":"","id":"2716","red":"224","green":"175","blue":"98","interior":"0","available":"0"},{"code":"V-398","name":"Foccacia Brown","headerimageurl":"","variant":"","file":"","imageurl":"","id":"2727","red":"202","green":"187","blue":"146","interior":"0","available":"0"},{"code":"V-400","name":"Snakeskin","headerimageurl":"","variant":"","file":"","imageurl":"","id":"2729","red":"133","green":"111","blue":"61","interior":"0","available":"0"},{"code":"V-408","name":"Runaway","headerimageurl":"","variant":"","file":"","imageurl":"","id":"2737","red":"137","green":"115","blue":"58","interior":"0","available":"0"},{"code":"V-480","name":"Sequoia Brown","headerimageurl":"","variant":"","file":"","imageurl":"","id":"2809","red":"145","green":"102","blue":"85","interior":"0","available":"0"},{"code":"V-492","name":"Pastrami Brown","headerimageurl":"","variant":"","file":"","imageurl":"","id":"2821","red":"117","green":"99","blue":"85","interior":"0","available":"0"},{"code":"V-508","name":"Caliga Brown","headerimageurl":"","variant":"","file":"","imageurl":"","id":"2837","red":"101","green":"83","blue":"59","interior":"0","available":"0"},{"code":"V-515","name":"Cottage Brown","headerimageurl":"","variant":"","file":"","imageurl":"","id":"2844","red":"185","green":"154","blue":"100","interior":"0","available":"0"},{"code":"V-518","name":"Retro Brown","headerimageurl":"","variant":"","file":"","imageurl":"","id":"2847","red":"215","green":"191","blue":"143","interior":"0","available":"0"},{"code":"V-737","name":"Carnelian","headerimageurl":"","variant":"","file":"","imageurl":"","id":"3066","red":"126","green":"69","blue":"58","interior":"0","available":"0"},{"code":"V-739","name":"Red on Brown","headerimageurl":"","variant":"","file":"","imageurl":"","id":"3068","red":"98","green":"62","blue":"62","interior":"0","available":"0"},{"code":"V-748","name":"Citadel Brown","headerimageurl":"","variant":"","file":"","imageurl":"","id":"3077","red":"137","green":"94","blue":"62","interior":"0","available":"0"},{"code":"BCT19-7809S","name":"Morning Cocoa","headerimageurl":"","variant":"","file":"","imageurl":"","id":"3151","red":"139","green":"122","blue":"116","interior":"0","available":"1"},{"code":"A-089-E","name":"\n*For interior only","headerimageurl":"","variant":"","file":"","imageurl":"","id":"3251","red":"139","green":"117","blue":"46","interior":"1","available":"1"},{"code":"A-090-E","name":"\n*For interior only","headerimageurl":"","variant":"","file":"","imageurl":"","id":"3252","red":"138","green":"118","blue":"61","interior":"1","available":"1"},{"code":"B&#8209;780","name":"Chocolate Brown","headerimageurl":"","variant":"","file":"","imageurl":"","id":"3415","red":"91","green":"81","blue":"76","interior":"0","available":"0"}]