[{"code":"B&#8209;600","name":"White","variant":"","file":"","imageurl":"","id":"3124","red":"242","green":"242","blue":"242"},{"code":"B&#8209;621","name":"Ivory","variant":"","file":"","imageurl":"","id":"235","red":"234","green":"183","blue":"123"},{"code":"B&#8209;630","name":"Silver Gray","variant":"","file":"","imageurl":"","id":"236","red":"137","green":"130","blue":"113"},{"code":"B&#8209;631","name":"Medium Gray","variant":"","file":"","imageurl":"","id":"237","red":"82","green":"98","blue":"107"},{"code":"B&#8209;640","name":"Royal Blue","variant":"","file":"","imageurl":"","id":"238","red":"3","green":"54","blue":"90"},{"code":"B&#8209;642","name":"Sky Blue","variant":"","file":"","imageurl":"","id":"239","red":"133","green":"206","blue":"225"},{"code":"B&#8209;647","name":"Delft Blue","variant":"","file":"","imageurl":"","id":"240","red":"0","green":"101","blue":"133"},{"code":"B&#8209;650","name":"Nile Green","variant":"","file":"","imageurl":"","id":"241","red":"123","green":"140","blue":"85"},{"code":"B&#8209;651","name":"Dark Green","variant":"","file":"","imageurl":"","id":"242","red":"30","green":"56","blue":"45"},{"code":"B&#8209;656","name":"Jade Green","variant":"","file":"","imageurl":""0,"id":"243","red":"31","green":"98","blue":"66"},{"code":"B&#8209;658","name":"Emerald Green","variant":"","file":"","imageurl":""1,"id":"244","red":"36","green":"65","blue":"51"},{"code":"B&#8209;661","name":"Lemon Yellow","variant":"","file":"","imageurl":""2,"id":"245","red":"255","green":"188","blue":"3"},{"code":"B&#8209;665","name":"Caterpillar Yellow","variant":"","file":"","imageurl":""3,"id":"246","red":"170","green":"115","blue":"45"},{"code":"B&#8209;670","name":"Bright Red","variant":"","file":"","imageurl":""4,"id":"247","red":"166","green":"10","blue":"33"},{"code":"B&#8209;671","name":"International Red","variant":"","file":"","imageurl":""5,"id":"248","red":"117","green":"25","blue":"23"},{"code":"B&#8209;673","name":"Maroon","variant":"","file":"","imageurl":""6,"id":"249","red":"83","green":"48","blue":"44"},{"code":"B&#8209;676","name":"Orange","variant":"","file":"","imageurl":""7,"id":"250","red":"210","green":"77","blue":"33"},{"code":"B&#8209;680","name":"Chocolate Brown","variant":"","file":"","imageurl":""8,"id":"251","red":"54","green":"37","blue":"35"},{"code":"B&#8209;681","name":"Mahogany","variant":"","file":"","imageurl":""9,"id":"252","red":"65","green":"42","blue":"43"},{"code":"B&#8209;683","name":"Caramel Brown","variant":"","file":"","imageurl":""0,"id":"253","red":"118","green":"75","blue":"59"},{"code":"B&#8209;685","name":"Sammy Brown","variant":"","file":"","imageurl":""1,"id":"254","red":"94","green":"81","blue":"62"},{"code":"B&#8209;690","name":"Black","variant":"","file":"","imageurl":""2,"id":"3125","red":"46","green":"48","blue":"50"},{"code":"","name":"* For site-mixing pastel to medium hues, use only <span class='boysen-name'>BOYSEN<span class='boysen-reg'>&reg;</span><span class='boysen-reg-holder'>&reg;</span></span> Oil Tinting Colors. For darker shades, you may request for factory-mixed colors by visiting accredited <span class='boysen-name'>BOYSEN<span class='boysen-reg'>&reg;</span><span class='boysen-reg-holder'>&reg;</span></span> dealers near or within your area.","variant":"","file":"","imageurl":""3,"id":0,"red":-1,"green":-1,"blue":-1}]