{"id":"94","name":"<span class='boysen-name'>BOYSEN<span class='boysen-reg'>&reg;</span><span class='boysen-reg-holder'>&reg;</span></span> Series G New Edition Volume 1 (July 2019)","subtitle":"","image":"data\/1094.jpg","url":"boysen-series-g-new-edition-volume-1-july-2019","imageurl":"https:\/\/files.boysencdn.com\/boysen\/uploads\/collection\/cover\/full\/1094.jpg","canimageurl":"","rgbhexcolor":"","imagelogourl":"https:\/\/files.boysencdn.com\/boysen\/uploads\/collection\/logo\/1094.png","imageweburl":"https:\/\/files.boysencdn.com\/boysen\/uploads\/product\/page\/full\/1094.jpg","imagewebmobileurl":"","bannerurl":"https:\/\/files.boysencdn.com\/boysen\/uploads\/collection\/full\/1094.jpg","colors":"135","techdata":"0","linkdata":[],"info":[]}