{"variants":[{"name":"","id":"0"}],"details":[{"name":"Form","info":"Powder","idx":0},{"name":"VOC (\u00b12.0 g\/L)","info":"0 g\/L","idx":0},{"name":"Pot Life","info":"60 to 90 minutes","idx":0},{"name":"Theoretical Coverage","info":"Approximately 1 sq.m. per 25-kg bag at 10mm application","idx":0},{"name":"Mixing Ratio","info":"3.25 to 3.50 Liters of water per 25-kg bag","idx":0},{"name":"Clean-up Solvent","info":"Water","idx":0},{"name":"Packaging","info":"25-kg bags","idx":0},{"name":"Application","info":"By trowel","idx":0}]}