[
    {"code":"BCP&#8209;1111","name":"Royal Wedding","reference":"I-A.1","variant":"","file":"","id":"1542","red":"247","green":"225","blue":"225"},
    {"code":"BCP&#8209;1104","name":"Valerie","reference":"I-A.2","variant":"","file":"","id":"1535","red":"250","green":"228","blue":"230"},
    {"code":"BCP&#8209;1097","name":"Pale Petunia","reference":"I-A.3","variant":"","file":"","id":"1528","red":"239","green":"189","blue":"196"},
    {"code":"BCP&#8209;1091","name":"All Dressed Up","reference":"I-A.4","variant":"","file":"","id":"1522","red":"243","green":"201","blue":"201"},
    {"code":"BCP&#8209;1084","name":"Go Go Pink","reference":"I-A.5","variant":"","file":"","id":"1515","red":"246","green":"211","blue":"207"},
    {"code":"BCP&#8209;1076","name":"Baby Blossom","reference":"I-A.6","variant":"","file":"","id":"1507","red":"247","green":"235","blue":"229"},
    {"code":"BCP&#8209;1070","name":"Peony Prize","reference":"I-A.7","variant":"","file":"","id":"1501","red":"245","green":"217","blue":"209"},
    {"code":"BCT19&#8209;7206S","name":"Cloud of Unknowing","reference":"I-A.8","variant":"","file":"","id":"3154","red":"235","green":"202","blue":"197"},
    {"code":"BCP&#8209;1056","name":"Elizabeth Rose","reference":"I-A.9","variant":"","file":"","id":"1487","red":"246","green":"219","blue":"207"},
    {"code":"BCP&#8209;1048","name":"Pale Shrimp","reference":"I-A.10","variant":"","file":"","id":"1479","red":"247","green":"222","blue":"213"},
    {"code":"BM&#8209;0211","name":"Fine Sand","reference":"I-A.11","variant":"","file":"","id":"2267","red":"244","green":"230","blue":"218"},
    {"code":"BSGV1&#8209;022","name":"Blossom Heart","reference":"I-A.12","variant":"","file":"","id":"1911","red":"243","green":"198","blue":"170"},
    {"code":"BCP&#8209;1021","name":"Sweet Buttermilk","reference":"I-A.13","variant":"","file":"","id":"1452","red":"250","green":"233","blue":"218"},
    {"code":"BCP&#8209;1041","name":"Flowerbed","reference":"I-A.14","variant":"","file":"","id":"1472","red":"252","green":"230","blue":"215"},
    {"code":"BCP&#8209;1013","name":"Warm Bread","reference":"I-A.15","variant":"","file":"","id":"1444","red":"246","green":"225","blue":"205"},
    {"code":"BCP&#8209;1006","name":"Turkscap","reference":"I-A.16","variant":"","file":"","id":"1437","red":"241","green":"211","blue":"187"},
    {"code":"BM&#8209;0011","name":"Seashell White","reference":"I-A.17","variant":"","file":"","id":"2067","red":"241","green":"225","blue":"212"},
    {"code":"BCP&#8209;0971","name":"May Sun","reference":"I-A.18","variant":"","file":"","id":"1402","red":"250","green":"232","blue":"208"},
    {"code":"BM&#8209;0053","name":"Peach Tart","reference":"I-A.19","variant":"","file":"","id":"2109","red":"246","green":"198","blue":"158"},
    {"code":"BCP&#8209;0957","name":"Pale Narcissus","reference":"I-A.20","variant":"","file":"","id":"1388","red":"250","green":"240","blue":"222"},
    {"code":"BM&#8209;0107","name":"Milky Bar","reference":"I-A.21","variant":"","file":"","id":"2163","red":"250","green":"239","blue":"217"},
    {"code":"BCP&#8209;1027","name":"Abstract White","reference":"I-A.22","variant":"","file":"","id":"1458","red":"247","green":"238","blue":"225"},
    {"code":"BCP&#8209;0999","name":"Ivory Tassel","reference":"I-A.23","variant":"","file":"","id":"1430","red":"245","green":"228","blue":"210"},
    {"code":"BCP&#8209;0992","name":"Touch of Topaz","reference":"I-A.24","variant":"","file":"","id":"1423","red":"243","green":"222","blue":"203"},
    {"code":"BM&#8209;0041","name":"Victorian White","reference":"I-A.25","variant":"","file":"","id":"2097","red":"246","green":"225","blue":"203"},
    {"code":"BCP&#8209;1113","name":"Fruitbowl","reference":"I-B.1","variant":"","file":"","id":"1544","red":"249","green":"205","blue":"211"},
    {"code":"BCP&#8209;1112","name":"Wishful Thinking","reference":"I-B.2","variant":"","file":"","id":"1543","red":"247","green":"217","blue":"220"},
    {"code":"BCP&#8209;1099","name":"Dimple","reference":"I-B.3","variant":"","file":"","id":"1530","red":"219","green":"126","blue":"136"},
    {"code":"BCP&#8209;1092","name":"Petals Unfolding","reference":"I-B.4","variant":"","file":"","id":"1523","red":"235","green":"184","blue":"188"},
    {"code":"BCP&#8209;1086","name":"Nosegay","reference":"I-B.5","variant":"","file":"","id":"1517","red":"239","green":"159","blue":"159"},
    {"code":"BM&#8209;0017","name":"Angel Face","reference":"I-B.6","variant":"","file":"","id":"2073","red":"252","green":"225","blue":"214"},
    {"code":"BCP&#8209;1071","name":"Cloud Number Nine","reference":"I-B.7","variant":"","file":"","id":"1502","red":"243","green":"202","blue":"194"},
    {"code":"BCP&#8209;1064","name":"Mystic Tulip","reference":"I-B.8","variant":"","file":"","id":"1495","red":"241","green":"173","blue":"160"},
    {"code":"BCP&#8209;1057","name":"Pink Satin","reference":"I-B.9","variant":"","file":"","id":"1488","red":"238","green":"193","blue":"176"},
    {"code":"BCP&#8209;1049","name":"Salmon Mousse","reference":"I-B.10","variant":"","file":"","id":"1480","red":"247","green":"204","blue":"192"},
    {"code":"BCP&#8209;1035","name":"Spiced Cider","reference":"I-B.11","variant":"","file":"","id":"1466","red":"240","green":"193","blue":"165"},
    {"code":"BSGV1&#8209;018","name":"Cozy Melon","reference":"I-B.12","variant":"","file":"","id":"183","red":"227","green":"170","blue":"147"},
    {"code":"BCT17&#8209;7717S","name":"Shimmer Shake","reference":"I-B.13","variant":"","file":"","id":"1823","red":"237","green":"149","blue":"103"},
    {"code":"BCP&#8209;1045","name":"Creamy Orange Blush","reference":"I-B.14","variant":"","file":"","id":"1476","red":"244","green":"151","blue":"121"},
    {"code":"BCP&#8209;1014","name":"Muffin Magic","reference":"I-B.15","variant":"","file":"","id":"1445","red":"247","green":"214","blue":"194"},
    {"code":"BCP&#8209;1007","name":"Pastel Peach","reference":"I-B.16","variant":"","file":"","id":"1438","red":"239","green":"198","blue":"171"},
    {"code":"BSGV1&#8209;023","name":"Santa Fe Sunset","reference":"I-B.17","variant":"","file":"","id":"1920","red":"245","green":"212","blue":"188"},
    {"code":"BCP&#8209;0972","name":"Apple Cider","reference":"I-B.18","variant":"","file":"","id":"1403","red":"252","green":"213","blue":"180"},
    {"code":"BCT14&#8209;7707S","name":"Walking on Sunshine","reference":"I-B.19","variant":"","file":"","id":"1774","red":"227","green":"166","blue":"112"},
    {"code":"BCP&#8209;0964","name":"Capetown Cream","reference":"I-B.20","variant":"","file":"","id":"1395","red":"251","green":"229","blue":"202"},
    {"code":"BCP&#8209;0965","name":"Gold of Midas","reference":"I-B.21","variant":"","file":"","id":"1396","red":"253","green":"229","blue":"197"},
    {"code":"BM&#8209;0034","name":"Smooth Cream","reference":"I-B.22","variant":"","file":"","id":"2090","red":"246","green":"221","blue":"197"},
    {"code":"BCP&#8209;1001","name":"Cheddar Corn","reference":"I-B.23","variant":"","file":"","id":"1432","red":"243","green":"206","blue":"178"},
    {"code":"BCP&#8209;0994","name":"Sparkle Glow","reference":"I-B.24","variant":"","file":"","id":"1425","red":"241","green":"205","blue":"178"},
    {"code":"BSGV1&#8209;026","name":"California Peach","reference":"I-B.25","variant":"","file":"","id":"184","red":"244","green":"191","blue":"150"},
    {"code":"BCP&#8209;1115","name":"Dollie","reference":"I-C.1","variant":"","file":"","id":"1546","red":"230","green":"139","blue":"156"},
    {"code":"BCP&#8209;1114","name":"A Lot of Love","reference":"I-C.2","variant":"","file":"","id":"1545","red":"249","green":"189","blue":"200"},
    {"code":"BCP&#8209;1100","name":"Heart to Heart","reference":"I-C.3","variant":"","file":"","id":"1531","red":"203","green":"90","blue":"99"},
    {"code":"BCP&#8209;1093","name":"Wood Nymph","reference":"I-C.4","variant":"","file":"","id":"1524","red":"226","green":"158","blue":"165"},
    {"code":"BCP&#8209;1087","name":"Bay Coral","reference":"I-C.5","variant":"","file":"","id":"1518","red":"223","green":"123","blue":"121"},
    {"code":"BCP&#8209;1079","name":"Wildflower Bouquet","reference":"I-C.6","variant":"","file":"","id":"1510","red":"250","green":"176","blue":"175"},
    {"code":"BCP&#8209;1072","name":"Lusty Orange","reference":"I-C.7","variant":"","file":"","id":"1503","red":"232","green":"172","blue":"163"},
    {"code":"BCP&#8209;1065","name":"Rose Essence","reference":"I-C.8","variant":"","file":"","id":"1496","red":"232","green":"150","blue":"134"},
    {"code":"BCP&#8209;1058","name":"Pale Terra","reference":"I-C.9","variant":"","file":"","id":"1489","red":"227","green":"166","blue":"148"},
    {"code":"BCP&#8209;1051","name":"Stucco Wall","reference":"I-C.10","variant":"","file":"","id":"1482","red":"234","green":"172","blue":"155"},
    {"code":"BCP&#8209;1037","name":"Trumpet Flower","reference":"I-C.11","variant":"","file":"","id":"1468","red":"220","green":"148","blue":"117"},
    {"code":"BSGV1&#8209;021","name":"Burma Road","reference":"I-C.12","variant":"","file":"","id":"1903","red":"211","green":"151","blue":"124"},
    {"code":"BCP&#8209;1024","name":"Pumpkin Hue","reference":"I-C.13","variant":"","file":"","id":"1455","red":"239","green":"157","blue":"119"},
    {"code":"BCP&#8209;1046","name":"Ballet Cream","reference":"I-C.14","variant":"","file":"","id":"1477","red":"241","green":"125","blue":"89"},
    {"code":"BCP&#8209;1015","name":"Canter Peach","reference":"I-C.15","variant":"","file":"","id":"1446","red":"242","green":"205","blue":"183"},
    {"code":"BCP&#8209;1009","name":"Bedtime Story","reference":"I-C.16","variant":"","file":"","id":"1440","red":"220","green":"171","blue":"143"},
    {"code":"B&#8209;7571","name":"Peach Medley","reference":"I-C.17","variant":"","file":"","id":"227","red":"238","green":"196","blue":"174"},
    {"code":"BCP&#8209;0975","name":"Downy Feather","reference":"I-C.18","variant":"","file":"","id":"1406","red":"247","green":"161","blue":"104"},
    {"code":"B&#8209;7566","name":"Ojay","reference":"I-C.19","variant":"","file":"","id":"225","red":"219","green":"158","blue":"101"},
    {"code":"B&#8209;7521","name":"Pure Ivory","reference":"I-C.20","variant":"","file":"","id":"212","red":"252","green":"223","blue":"189"},
    {"code":"BCT16&#8209;7711S","name":"Weekender","reference":"I-C.21","variant":"","file":"","id":"1780","red":"245","green":"126","blue":"46"},
    {"code":"BSGV1&#8209;036","name":"Desert Dust","reference":"I-C.22","variant":"","file":"","id":"1916","red":"243","green":"199","blue":"168"},
    {"code":"BCP&#8209;1002","name":"Tea Cookie","reference":"I-C.23","variant":"","file":"","id":"1433","red":"220","green":"178","blue":"150"},
    {"code":"BCP&#8209;0995","name":"Bread Pudding","reference":"I-C.24","variant":"","file":"","id":"1426","red":"230","green":"185","blue":"149"},
    {"code":"BM&#8209;0055","name":"Pumpkin Patch","reference":"I-C.25","variant":"","file":"","id":"2111","red":"228","green":"162","blue":"111"},
    {"code":"BCT19&#8209;7725S","name":"Red Thunder","reference":"I-D.1","variant":"","file":"","id":"3139","red":"186","green":"21","blue":"38"},
    {"code":"BCP&#8209;1116","name":"Movie Star","reference":"I-D.2","variant":"","file":"","id":"1547","red":"184","green":"46","blue":"56"},
    {"code":"BCP&#8209;1102","name":"Precious Peony","reference":"I-D.3","variant":"","file":"","id":"1533","red":"180","green":"68","blue":"72"},
    {"code":"BCP&#8209;1094","name":"Porcelain Rose","reference":"I-D.4","variant":"","file":"","id":"1525","red":"209","green":"127","blue":"134"},
    {"code":"BCP&#8209;1088","name":"Childhood Crush","reference":"I-D.5","variant":"","file":"","id":"1519","red":"213","green":"105","blue":"102"},
    {"code":"BCT20&#8209;7731S","name":"Razzle Dazzle","reference":"I-D.6","variant":"","file":"","id":"3370","red":"163","green":"67","blue":"72"},
    {"code":"BCP&#8209;1074","name":"It's My Party","reference":"I-D.7","variant":"","file":"","id":"1505","red":"196","green":"112","blue":"101"},
    {"code":"BCP&#8209;1066","name":"Sari","reference":"I-D.8","variant":"","file":"","id":"1497","red":"217","green":"120","blue":"98"},
    {"code":"BCP&#8209;1060","name":"First Lady","reference":"I-D.9","variant":"","file":"","id":"1491","red":"189","green":"119","blue":"103"},
    {"code":"BCP&#8209;1052","name":"Summer Memory","reference":"I-D.10","variant":"","file":"","id":"1483","red":"213","green":"128","blue":"109"},
    {"code":"BCP&#8209;1038","name":"Jack-O-Lantern","reference":"I-D.11","variant":"","file":"","id":"1469","red":"204","green":"118","blue":"83"},
    {"code":"BSGV1&#8209;016","name":"Bitter Sweet","reference":"I-D.12","variant":"","file":"","id":"168","red":"191","green":"106","blue":"91"},
    {"code":"BCP&#8209;1026","name":"Casa De Oro","reference":"I-D.13","variant":"","file":"","id":"1457","red":"198","green":"100","blue":"60"},
    {"code":"BCT19&#8209;7726S","name":"Sunset March","reference":"I-D.14","variant":"","file":"","id":"3141","red":"229","green":"86","blue":"42"},
    {"code":"BCP&#8209;1017","name":"Summer's End","reference":"I-D.15","variant":"","file":"","id":"1448","red":"213","green":"140","blue":"101"},
    {"code":"BSGV1&#8209;025","name":"Papaya","reference":"I-D.16","variant":"","file":"","id":"167","red":"195","green":"139","blue":"106"},
    {"code":"BSGV1&#8209;013","name":"Lotus Blossom","reference":"I-D.17","variant":"","file":"","id":"1905","red":"241","green":"185","blue":"165"},
    {"code":"BM&#8209;0088","name":"Tangerinette","reference":"I-D.18","variant":"","file":"","id":"2144","red":"245","green":"144","blue":"72"},
    {"code":"BCT20&#8209;7732S","name":"Sunset Dream","reference":"I-D.19","variant":"","file":"","id":"3373","red":"201","green":"119","blue":"82"},
    {"code":"BCP&#8209;0969","name":"Au Gratin","reference":"I-D.20","variant":"","file":"","id":"1400","red":"254","green":"148","blue":"72"},
    {"code":"BCP&#8209;1033","name":"Lava Lamp","reference":"I-D.21","variant":"","file":"","id":"1464","red":"223","green":"109","blue":"57"},
    {"code":"BM&#8209;0032","name":"Big Bounce","reference":"I-D.22","variant":"","file":"","id":"2088","red":"213","green":"141","blue":"108"},
    {"code":"BCP&#8209;1004","name":"Peace of Mind","reference":"I-D.23","variant":"","file":"","id":"1435","red":"188","green":"131","blue":"96"},
    {"code":"BCP&#8209;0996","name":"Spice Cookie","reference":"I-D.24","variant":"","file":"","id":"1427","red":"211","green":"151","blue":"107"},
    {"code":"BSGV1&#8209;028","name":"Copper Bright","reference":"I-D.25","variant":"","file":"","id":"185","red":"206","green":"145","blue":"100"},
    {"code":"BCT17&#8209;7715S","name":"Mystical Jar","reference":"I-E.1","variant":"","file":"","id":"1828","red":"175","green":"22","blue":"42"},
    {"code":"BCT16&#8209;7712S","name":"Saffron Burst","reference":"I-E.2","variant":"","file":"","id":"1794","red":"161","green":"41","blue":"40"},
    {"code":"BCP&#8209;1103","name":"Moonrose","reference":"I-E.3","variant":"","file":"","id":"1534","red":"156","green":"64","blue":"71"},
    {"code":"BCP&#8209;1095","name":"Empower","reference":"I-E.4","variant":"","file":"","id":"1526","red":"168","green":"73","blue":"71"},
    {"code":"BCP&#8209;1089","name":"Chuckles","reference":"I-E.5","variant":"","file":"","id":"1520","red":"180","green":"67","blue":"59"},
    {"code":"BCT18&#8209;7724S","name":"Hot Rod","reference":"I-E.6","variant":"","file":"","id":"1841","red":"197","green":"35","blue":"22"},
    {"code":"BCP&#8209;1075","name":"Cherry Blink","reference":"I-E.7","variant":"","file":"","id":"1506","red":"166","green":"82","blue":"69"},
    {"code":"BCP&#8209;1067","name":"Sweet Baby Rose","reference":"I-E.8","variant":"","file":"","id":"1498","red":"182","green":"79","blue":"64"},
    {"code":"BCP&#8209;1061","name":"April Love","reference":"I-E.9","variant":"","file":"","id":"1492","red":"136","green":"68","blue":"55"},
    {"code":"BCP&#8209;1053","name":"Sun's Rage","reference":"I-E.10","variant":"","file":"","id":"1484","red":"163","green":"78","blue":"56"},
    {"code":"BCP&#8209;1039","name":"Pretty Parasol","reference":"I-E.11","variant":"","file":"","id":"1470","red":"167","green":"95","blue":"67"},
    {"code":"BM&#8209;0012","name":"Berrylicious","reference":"I-E.12","variant":"","file":"","id":"2068","red":"164","green":"85","blue":"73"},
    {"code":"BSGV1&#8209;020","name":"Sand Dance","reference":"I-E.13","variant":"","file":"","id":"1902","red":"175","green":"111","blue":"80"},
    {"code":"BCT14&#8209;7703S","name":"Cerise Street","reference":"I-E.14","variant":"","file":"","id":"1761","red":"212","green":"70","blue":"48"},
    {"code":"BCP&#8209;1019","name":"Orange Ballad","reference":"I-E.15","variant":"","file":"","id":"1450","red":"174","green":"105","blue":"66"},
    {"code":"BCP&#8209;1012","name":"Hampton Beach","reference":"I-E.16","variant":"","file":"","id":"1443","red":"153","green":"93","blue":"59"},
    {"code":"B&#8209;7580","name":"Nuevo Terra","reference":"I-E.17","variant":"","file":"","id":"228","red":"206","green":"136","blue":"110"},
    {"code":"BSGV1&#8209;033","name":"Orange Royale","reference":"I-E.18","variant":"","file":"","id":"194","red":"232","green":"119","blue":"61"},
    {"code":"BCT16&#8209;7710S","name":"Dune Buggy","reference":"I-E.19","variant":"","file":"","id":"1802","red":"210","green":"123","blue":"54"},
    {"code":"BCP&#8209;0963","name":"Zambia","reference":"I-E.20","variant":"","file":"","id":"1394","red":"255","green":"141","blue":"30"},
    {"code":"BCP&#8209;1081","name":"Endless Possibilities","reference":"I-E.21","variant":"","file":"","id":"1512","red":"210","green":"68","blue":"57"},
    {"code":"BSGV1&#8209;034","name":"Ablaze","reference":"I-E.22","variant":"","file":"","id":"181","red":"214","green":"127","blue":"86"},
    {"code":"BCP&#8209;1005","name":"Flickering Flame","reference":"I-E.23","variant":"","file":"","id":"1436","red":"165","green":"107","blue":"75"},
    {"code":"BCP&#8209;0998","name":"Gold Metal","reference":"I-E.24","variant":"","file":"","id":"1429","red":"175","green":"115","blue":"70"},
    {"code":"BCT19&#8209;7611S","name":"Majestic Mare","reference":"I-E.25","variant":"","file":"","id":"3157","red":"166","green":"106","blue":"20"},
    {"code":"BCP&#8209;0936","name":"Diantha","reference":"I-F.1","variant":"","file":"","id":"1367","red":"253","green":"240","blue":"217"},
    {"code":"BCP&#8209;0930","name":"Marshmallow Fluff","reference":"I-F.2","variant":"","file":"","id":"1361","red":"248","green":"238","blue":"217"},
    {"code":"BM&#8209;0145","name":"Blissful","reference":"I-F.3","variant":"","file":"","id":"2201","red":"240","green":"236","blue":"214"},
    {"code":"BCP&#8209;0922","name":"Cheesecake","reference":"I-F.4","variant":"","file":"","id":"1353","red":"245","green":"234","blue":"210"},
    {"code":"BCP&#8209;0915","name":"Queenly Laugh","reference":"I-F.5","variant":"","file":"","id":"1346","red":"247","green":"230","blue":"203"},
    {"code":"BCP&#8209;0817","name":"Best of Summer","reference":"I-F.6","variant":"","file":"","id":"1248","red":"247","green":"237","blue":"212"},
    {"code":"B&#8209;7504","name":"Coast Light","reference":"I-F.7","variant":"","file":"","id":"201","red":"251","green":"235","blue":"209"},
    {"code":"BM&#8209;0105","name":"White Spark","reference":"I-F.8","variant":"","file":"","id":"2161","red":"248","green":"242","blue":"219"},
    {"code":"BCP&#8209;0831","name":"Lavish Lemon","reference":"I-F.9","variant":"","file":"","id":"1262","red":"249","green":"234","blue":"198"},
    {"code":"BCP&#8209;0825","name":"Frozen Banana","reference":"I-F.10","variant":"","file":"","id":"1256","red":"250","green":"239","blue":"208"},
    {"code":"BCP&#8209;0908","name":"God-Given","reference":"I-F.11","variant":"","file":"","id":"1339","red":"249","green":"239","blue":"222"},
    {"code":"BCP&#8209;0852","name":"Touch Of Sun","reference":"I-F.12","variant":"","file":"","id":"1283","red":"248","green":"243","blue":"228"},
    {"code":"BM&#8209;0063","name":"Spring Shoot","reference":"I-F.13","variant":"","file":"","id":"2119","red":"245","green":"229","blue":"193"},
    {"code":"BCP&#8209;0985","name":"Whiskers","reference":"I-F.14","variant":"","file":"","id":"1416","red":"248","green":"237","blue":"224"},
    {"code":"BCP&#8209;0901","name":"Spinning Wheel","reference":"I-F.15","variant":"","file":"","id":"1332","red":"246","green":"234","blue":"214"},
    {"code":"BCP&#8209;0894","name":"Misty Mustard","reference":"I-F.16","variant":"","file":"","id":"1325","red":"246","green":"229","blue":"205"},
    {"code":"BCP&#8209;0887","name":"Haystack","reference":"I-F.17","variant":"","file":"","id":"1318","red":"241","green":"223","blue":"197"},
    {"code":"BCP&#8209;0880","name":"Cauliflower Cream","reference":"I-F.18","variant":"","file":"","id":"1311","red":"241","green":"222","blue":"196"},
    {"code":"BCP&#8209;0873","name":"Washed in Light","reference":"I-F.19","variant":"","file":"","id":"1304","red":"249","green":"227","blue":"196"},
    {"code":"BCP&#8209;0866","name":"Apple Sauce","reference":"I-F.20","variant":"","file":"","id":"1297","red":"243","green":"230","blue":"205"},
    {"code":"BCP&#8209;0859","name":"Daylilly Yellow","reference":"I-F.21","variant":"","file":"","id":"1290","red":"248","green":"234","blue":"205"},
    {"code":"BCP&#8209;0845","name":"Lemon Stick","reference":"I-F.22","variant":"","file":"","id":"1276","red":"249","green":"242","blue":"219"},
    {"code":"BCP&#8209;0838","name":"Fresh Cream","reference":"I-F.23","variant":"","file":"","id":"1269","red":"249","green":"242","blue":"219"},
    {"code":"BM&#8209;0069","name":"Sunshiny","reference":"I-F.24","variant":"","file":"","id":"2125","red":"245","green":"223","blue":"182"},
    {"code":"BCP&#8209;0810","name":"Annabel","reference":"I-F.25","variant":"","file":"","id":"1241","red":"245","green":"233","blue":"200"},
    {"code":"B&#8209;7560","name":"Yellow Ware","reference":"I-G.1","variant":"","file":"","id":"224","red":"255","green":"217","blue":"134"},
    {"code":"BM&#8209;0073","name":"Summer's Day","reference":"I-G.2","variant":"","file":"","id":"2129","red":"250","green":"223","blue":"171"},
    {"code":"B&#8209;7513","name":"Crisp Ecru","reference":"I-G.3","variant":"","file":"","id":"209","red":"248","green":"231","blue":"205"},
    {"code":"BCP&#8209;0923","name":"Tiffany Light","reference":"I-G.4","variant":"","file":"","id":"1354","red":"255","green":"221","blue":"177"},
    {"code":"BCP&#8209;0916","name":"Honey Cream","reference":"I-G.5","variant":"","file":"","id":"1347","red":"249","green":"229","blue":"201"},
    {"code":"BCP&#8209;0819","name":"Lemon Tint","reference":"I-G.6","variant":"","file":"","id":"1250","red":"253","green":"237","blue":"200"},
    {"code":"BM&#8209;0061","name":"Sunny Smile","reference":"I-G.7","variant":"","file":"","id":"2117","red":"247","green":"231","blue":"195"},
    {"code":"BCP&#8209;0951","name":"Pound Cake","reference":"I-G.8","variant":"","file":"","id":"1382","red":"254","green":"235","blue":"194"},
    {"code":"BCP&#8209;0833","name":"Scene Stealer","reference":"I-G.9","variant":"","file":"","id":"1264","red":"254","green":"223","blue":"151"},
    {"code":"BCP&#8209;0827","name":"Ray of Light","reference":"I-G.10","variant":"","file":"","id":"1258","red":"255","green":"235","blue":"186"},
    {"code":"BCP&#8209;0909","name":"Autumn Child","reference":"I-G.11","variant":"","file":"","id":"1340","red":"251","green":"224","blue":"189"},
    {"code":"BM&#8209;0091","name":"Honey Star","reference":"I-G.12","variant":"","file":"","id":"2147","red":"238","green":"216","blue":"182"},
    {"code":"BM&#8209;0067","name":"Creamy Candy","reference":"I-G.13","variant":"","file":"","id":"2123","red":"248","green":"221","blue":"108"},
    {"code":"BCP&#8209;0986","name":"Mineral Glow","reference":"I-G.14","variant":"","file":"","id":"1417","red":"250","green":"227","blue":"204"},
    {"code":"BCP&#8209;0903","name":"Dainty Flower","reference":"I-G.15","variant":"","file":"","id":"1334","red":"244","green":"206","blue":"162"},
    {"code":"BCP&#8209;0895","name":"Rotunda Gold","reference":"I-G.16","variant":"","file":"","id":"1326","red":"245","green":"218","blue":"186"},
    {"code":"BCP&#8209;0889","name":"Russeau Gold","reference":"I-G.17","variant":"","file":"","id":"1320","red":"233","green":"207","blue":"172"},
    {"code":"BCP&#8209;0882","name":"Marzipan","reference":"I-G.18","variant":"","file":"","id":"1313","red":"232","green":"205","blue":"167"},
    {"code":"BCP&#8209;0875","name":"Nothing Less","reference":"I-G.19","variant":"","file":"","id":"1306","red":"241","green":"215","blue":"181"},
    {"code":"BCP&#8209;0867","name":"Egg Noodle","reference":"I-G.20","variant":"","file":"","id":"1298","red":"242","green":"221","blue":"186"},
    {"code":"BCP&#8209;0860","name":"Hawaiian Cream","reference":"I-G.21","variant":"","file":"","id":"1291","red":"252","green":"226","blue":"181"},
    {"code":"BCP&#8209;0847","name":"Yellow Blitz","reference":"I-G.22","variant":"","file":"","id":"1278","red":"254","green":"237","blue":"182"},
    {"code":"BCP&#8209;0839","name":"Butterball","reference":"I-G.23","variant":"","file":"","id":"1270","red":"255","green":"237","blue":"194"},
    {"code":"BM&#8209;0058","name":"Buttercup","reference":"I-G.24","variant":"","file":"","id":"2114","red":"255","green":"223","blue":"172"},
    {"code":"BCP&#8209;0812","name":"Gold Strand","reference":"I-G.25","variant":"","file":"","id":"1243","red":"244","green":"216","blue":"162"},
    {"code":"BCP&#8209;0858","name":"Look At The Bright Side","reference":"I-H.1","variant":"","file":"","id":"1289","red":"255","green":"181","blue":"0"},
    {"code":"BCP&#8209;0932","name":"Sun Splashed","reference":"I-H.2","variant":"","file":"","id":"1363","red":"250","green":"207","blue":"146"},
    {"code":"BM&#8209;0075","name":"Sun Blessed","reference":"I-H.3","variant":"","file":"","id":"2131","red":"255","green":"219","blue":"162"},
    {"code":"BCP&#8209;0925","name":"Jonquil Trail","reference":"I-H.4","variant":"","file":"","id":"1356","red":"247","green":"203","blue":"147"},
    {"code":"BCP&#8209;0917","name":"Canyon Sand","reference":"I-H.5","variant":"","file":"","id":"1348","red":"241","green":"207","blue":"167"},
    {"code":"BCP&#8209;0820","name":"Sign of the Crown","reference":"I-H.6","variant":"","file":"","id":"1251","red":"254","green":"217","blue":"149"},
    {"code":"B&#8209;7525","name":"Bone Ivory","reference":"I-H.7","variant":"","file":"","id":"216","red":"233","green":"209","blue":"171"},
    {"code":"BCT14&#8209;7602S","name":"Kinder Yellow","reference":"I-H.8","variant":"","file":"","id":"1760","red":"238","green":"216","blue":"130"},
    {"code":"BCP&#8209;0835","name":"Glitter Yellow","reference":"I-H.9","variant":"","file":"","id":"1266","red":"251","green":"205","blue":"89"},
    {"code":"BCP&#8209;0829","name":"Dandy Lion","reference":"I-H.10","variant":"","file":"","id":"1260","red":"250","green":"194","blue":"80"},
    {"code":"BCP&#8209;0910","name":"Western Sky","reference":"I-H.11","variant":"","file":"","id":"1341","red":"251","green":"213","blue":"165"},
    {"code":"BSGV1&#8209;045","name":"Sunshine","reference":"I-H.12","variant":"","file":"","id":"1915","red":"235","green":"200","blue":"156"},
    {"code":"BSGV1&#8209;044","name":"Indian Corn","reference":"I-H.13","variant":"","file":"","id":"1913","red":"238","green":"191","blue":"145"},
    {"code":"BCP&#8209;0987","name":"Tallow","reference":"I-H.14","variant":"","file":"","id":"1418","red":"243","green":"204","blue":"170"},
    {"code":"BCP&#8209;0905","name":"Egyptian Gold","reference":"I-H.15","variant":"","file":"","id":"1336","red":"232","green":"187","blue":"133"},
    {"code":"BCP&#8209;0896","name":"Coin Purse","reference":"I-H.16","variant":"","file":"","id":"1327","red":"238","green":"205","blue":"168"},
    {"code":"BCP&#8209;0890","name":"Dubloon","reference":"I-H.17","variant":"","file":"","id":"1321","red":"213","green":"177","blue":"135"},
    {"code":"BCP&#8209;0883","name":"Follow the Leader","reference":"I-H.18","variant":"","file":"","id":"1314","red":"220","green":"190","blue":"149"},
    {"code":"BCP&#8209;0876","name":"Corn Chowder","reference":"I-H.19","variant":"","file":"","id":"1307","red":"223","green":"189","blue":"144"},
    {"code":"BCP&#8209;0869","name":"Frozen Fruit","reference":"I-H.20","variant":"","file":"","id":"1300","red":"226","green":"196","blue":"151"},
    {"code":"BCP&#8209;0862","name":"Yellow Trumpet","reference":"I-H.21","variant":"","file":"","id":"1293","red":"250","green":"208","blue":"135"},
    {"code":"BCP&#8209;0848","name":"Yellow Tail","reference":"I-H.22","variant":"","file":"","id":"1279","red":"255","green":"231","blue":"151"},
    {"code":"BCP&#8209;0841","name":"Sun's Glory","reference":"I-H.23","variant":"","file":"","id":"1272","red":"255","green":"215","blue":"100"},
    {"code":"BCT20&#8209;7615S","name":"Playtime","reference":"I-H.24","variant":"","file":"","id":"3372","red":"255","green":"233","blue":"166"},
    {"code":"BCP&#8209;0813","name":"Glistening","reference":"I-H.25","variant":"","file":"","id":"1244","red":"238","green":"202","blue":"132"},
    {"code":"BCP&#8209;0956","name":"I Love to Boogie","reference":"I-I.1","variant":"","file":"","id":"1387","red":"251","green":"159","blue":"2"},
    {"code":"BCP&#8209;0934","name":"Lemon Essence","reference":"I-I.2","variant":"","file":"","id":"1365","red":"224","green":"165","blue":"81"},
    {"code":"BM&#8209;0068","name":"Gold Truffles","reference":"I-I.3","variant":"","file":"","id":"2124","red":"214","green":"167","blue":"103"},
    {"code":"BCP&#8209;0927","name":"Lemon Poppy","reference":"I-I.4","variant":"","file":"","id":"1358","red":"224","green":"165","blue":"89"},
    {"code":"BM&#8209;0047","name":"Full Moon","reference":"I-I.5","variant":"","file":"","id":"2103","red":"242","green":"210","blue":"168"},
    {"code":"BCT16&#8209;7604S","name":"Tribute Yellow","reference":"I-I.6","variant":"","file":"","id":"1800","red":"244","green":"195","blue":"93"},
    {"code":"BM&#8209;0084","name":"Honey Jar","reference":"I-I.7","variant":"","file":"","id":"2140","red":"240","green":"207","blue":"168"},
    {"code":"BCT18&#8209;7608S","name":"Marquee Moon","reference":"I-I.8","variant":"","file":"","id":"1833","red":"251","green":"209","blue":"61"},
    {"code":"BCP&#8209;0836","name":"Basket of Gold","reference":"I-I.9","variant":"","file":"","id":"1267","red":"247","green":"193","blue":"61"},
    {"code":"BCT20&#8209;7616S","name":"Wildflowers","reference":"I-I.10","variant":"","file":"","id":"3375","red":"242","green":"185","blue":"70"},
    {"code":"BCP&#8209;0912","name":"Tropical Dream","reference":"I-I.11","variant":"","file":"","id":"1343","red":"230","green":"175","blue":"114"},
    {"code":"BCT18&#8209;7609S","name":"Work From Home","reference":"I-I.12","variant":"","file":"","id":"1840","red":"230","green":"202","blue":"154"},
    {"code":"BM&#8209;0081","name":"Cozy Yellow","reference":"I-I.13","variant":"","file":"","id":"2137","red":"233","green":"181","blue":"120"},
    {"code":"BCP&#8209;0988","name":"Mom's Apple Pie","reference":"I-I.14","variant":"","file":"","id":"1419","red":"233","green":"178","blue":"128"},
    {"code":"BCP&#8209;0906","name":"Cat's Eye Marble","reference":"I-I.15","variant":"","file":"","id":"1337","red":"213","green":"160","blue":"96"},
    {"code":"BCP&#8209;0898","name":"Goby Desert","reference":"I-I.16","variant":"","file":"","id":"1329","red":"209","green":"163","blue":"111"},
    {"code":"BCP&#8209;0891","name":"Silence is Golden","reference":"I-I.17","variant":"","file":"","id":"1322","red":"191","green":"153","blue":"108"},
    {"code":"BCP&#8209;0884","name":"Gold Tweed","reference":"I-I.18","variant":"","file":"","id":"1315","red":"202","green":"166","blue":"116"},
    {"code":"BCP&#8209;0877","name":"Gold Digger","reference":"I-I.19","variant":"","file":"","id":"1308","red":"208","green":"168","blue":"116"},
    {"code":"BCP&#8209;0870","name":"Lemon Slice","reference":"I-I.20","variant":"","file":"","id":"1301","red":"195","green":"158","blue":"96"},
    {"code":"BCP&#8209;0863","name":"I'm a Local","reference":"I-I.21","variant":"","file":"","id":"1294","red":"235","green":"181","blue":"92"},
    {"code":"BCP&#8209;0850","name":"Citron","reference":"I-I.22","variant":"","file":"","id":"1281","red":"255","green":"213","blue":"68"},
    {"code":"BCP&#8209;0843","name":"Buttered Popcorn","reference":"I-I.23","variant":"","file":"","id":"1274","red":"247","green":"191","blue":"4"},
    {"code":"BCT14&#8209;7601S","name":"Gold Charms","reference":"I-I.24","variant":"","file":"","id":"1771","red":"236","green":"199","blue":"85"},
    {"code":"BCP&#8209;0815","name":"Lemon Surprise","reference":"I-I.25","variant":"","file":"","id":"1246","red":"226","green":"179","blue":"92"},
    {"code":"BCT14&#8209;7706S","name":"Radioactive Orange","reference":"I-J.1","variant":"","file":"","id":"1762","red":"232","green":"156","blue":"70"},
    {"code":"BCP&#8209;0935","name":"Yellow Shout","reference":"I-J.2","variant":"","file":"","id":"1366","red":"207","green":"144","blue":"56"},
    {"code":"BSGV1&#8209;043","name":"Petal","reference":"I-J.3","variant":"","file":"","id":"1912","red":"221","green":"170","blue":"93"},
    {"code":"BCP&#8209;0928","name":"Yellow Warning","reference":"I-J.4","variant":"","file":"","id":"1359","red":"196","green":"137","blue":"61"},
    {"code":"BCP&#8209;0921","name":"Waxen Moon","reference":"I-J.5","variant":"","file":"","id":"1352","red":"178","green":"126","blue":"69"},
    {"code":"BCP&#8209;0823","name":"Sun Drops","reference":"I-J.6","variant":"","file":"","id":"1254","red":"234","green":"165","blue":"29"},
    {"code":"BCP&#8209;0920","name":"Sunrise Heat","reference":"I-J.7","variant":"","file":"","id":"1351","red":"200","green":"154","blue":"97"},
    {"code":"BCT19&#8209;7610S","name":"Liberty Bloc","reference":"I-J.8","variant":"","file":"","id":"3142","red":"241","green":"177","blue":"3"},
    {"code":"BCP&#8209;0837","name":"Fresh Scent","reference":"I-J.9","variant":"","file":"","id":"1268","red":"244","green":"182","blue":"34"},
    {"code":"BCT16&#8209;7605S","name":"Golden Nugget","reference":"I-J.10","variant":"","file":"","id":"1793","red":"244","green":"184","blue":"26"},
    {"code":"BCP&#8209;0914","name":"Child of the Moon","reference":"I-J.11","variant":"","file":"","id":"1345","red":"199","green":"136","blue":"63"},
    {"code":"BM&#8209;0099","name":"Biscotti","reference":"I-J.12","variant":"","file":"","id":"2155","red":"224","green":"192","blue":"154"},
    {"code":"BSGV1&#8209;042","name":"Golden","reference":"I-J.13","variant":"","file":"","id":"186","red":"213","green":"159","blue":"97"},
    {"code":"BCP&#8209;0991","name":"Beeswax Candle","reference":"I-J.14","variant":"","file":"","id":"1422","red":"188","green":"123","blue":"69"},
    {"code":"BCP&#8209;0907","name":"Millionaire","reference":"I-J.15","variant":"","file":"","id":"1338","red":"181","green":"128","blue":"62"},
    {"code":"BCP&#8209;0900","name":"Unforgettably Gold","reference":"I-J.16","variant":"","file":"","id":"1331","red":"173","green":"126","blue":"72"},
    {"code":"BCP&#8209;0893","name":"Rich And Rare","reference":"I-J.17","variant":"","file":"","id":"1324","red":"152","green":"116","blue":"73"},
    {"code":"BCP&#8209;0886","name":"Gold Estate","reference":"I-J.18","variant":"","file":"","id":"1317","red":"152","green":"119","blue":"71"},
    {"code":"BCP&#8209;0879","name":"Golden Cadillac","reference":"I-J.19","variant":"","file":"","id":"1310","red":"171","green":"129","blue":"75"},
    {"code":"BCP&#8209;0872","name":"Saffron Valley","reference":"I-J.20","variant":"","file":"","id":"1303","red":"167","green":"127","blue":"65"},
    {"code":"BCP&#8209;0865","name":"Lemon Bar","reference":"I-J.21","variant":"","file":"","id":"1296","red":"209","green":"154","blue":"57"},
    {"code":"BCT17&#8209;7606S","name":"Glow with the Flow","reference":"I-J.22","variant":"","file":"","id":"1821","red":"249","green":"231","blue":"0"},
    {"code":"BCT19&#8209;7613S","name":"Emoji Master","reference":"I-J.23","variant":"","file":"","id":"3148","red":"220","green":"194","blue":"3"},
    {"code":"BCT18&#8209;7607S","name":"Yellowstone Park","reference":"I-J.24","variant":"","file":"","id":"1846","red":"204","green":"160","blue":"12"},
    {"code":"BCP&#8209;0816","name":"Sin City","reference":"I-J.25","variant":"","file":"","id":"1247","red":"207","green":"155","blue":"56"}
]